Workbook

Sheet Parts
A1: Fictional parts. Type each part once with its unit cost (A5:B30, yellow).
A4: Part | B4: Unit cost
A5: Soap bar, oatmeal | B5: 1.85
A6: Soy candle, 8 oz | B6: 4.1
A7: Enamel mug | B7: 3.6
A8: Tea sample tin | B8: 1.4
A9: Gift box | B9: 0.95
A10: Tissue paper sheet | B10: 0.18
A11: Ribbon, 1 yd | B11: 0.12

Sheet Sets
A1: Fictional gift sets. Lines on the left (A5:C54, yellow): set name, part, quantity. Sets on the right (F5:F10, H5:H10, yellow): name and selling price.
A4: Set | B4: Part | C4: Qty | D4: Line cost | F4: Set | G4: Cost | H4: Price | I4: Margin | J4: Profit | K4: Status
A5: Spa Set | B5: Soap bar, oatmeal | C5: 2 | D5: =IF(B5="","",IF(NOT(ISNUMBER(C5)),"Check qty",IFERROR(ROUND(C5*INDEX(Parts!$B$5:$B$30,MATCH(B5,Parts!$A$5:$A$30,0)),2),"Missing part"))) | F5: Spa Set | G5: =IF(F5="","",SUMIF($A$5:$A$54,F5,$D$5:$D$54)) | H5: 24 | I5: =IF(F5="","",IF(AND(ISNUMBER(H5),H5>0),(H5-G5)/H5,"")) | J5: =IF(F5="","",IF(ISNUMBER(H5),H5-G5,"")) | K5: =IF(F5="","",IF(COUNTIF($A$5:$A$54,F5)=0,"No lines",IF(COUNTIFS($A$5:$A$54,F5,$D$5:$D$54,"Missing part")+COUNTIFS($A$5:$A$54,F5,$D$5:$D$54,"Check qty")>0,"Fix lines","OK")))
A6: Spa Set | B6: Soy candle, 8 oz | C6: 1 | D6: =IF(B6="","",IF(NOT(ISNUMBER(C6)),"Check qty",IFERROR(ROUND(C6*INDEX(Parts!$B$5:$B$30,MATCH(B6,Parts!$A$5:$A$30,0)),2),"Missing part"))) | F6: Cozy Mug Set | G6: =IF(F6="","",SUMIF($A$5:$A$54,F6,$D$5:$D$54)) | H6: 22 | I6: =IF(F6="","",IF(AND(ISNUMBER(H6),H6>0),(H6-G6)/H6,"")) | J6: =IF(F6="","",IF(ISNUMBER(H6),H6-G6,"")) | K6: =IF(F6="","",IF(COUNTIF($A$5:$A$54,F6)=0,"No lines",IF(COUNTIFS($A$5:$A$54,F6,$D$5:$D$54,"Missing part")+COUNTIFS($A$5:$A$54,F6,$D$5:$D$54,"Check qty")>0,"Fix lines","OK")))
A7: Spa Set | B7: Gift box | C7: 1 | D7: =IF(B7="","",IF(NOT(ISNUMBER(C7)),"Check qty",IFERROR(ROUND(C7*INDEX(Parts!$B$5:$B$30,MATCH(B7,Parts!$A$5:$A$30,0)),2),"Missing part"))) | F7: Candle Duo | G7: =IF(F7="","",SUMIF($A$5:$A$54,F7,$D$5:$D$54)) | H7: 20 | I7: =IF(F7="","",IF(AND(ISNUMBER(H7),H7>0),(H7-G7)/H7,"")) | J7: =IF(F7="","",IF(ISNUMBER(H7),H7-G7,"")) | K7: =IF(F7="","",IF(COUNTIF($A$5:$A$54,F7)=0,"No lines",IF(COUNTIFS($A$5:$A$54,F7,$D$5:$D$54,"Missing part")+COUNTIFS($A$5:$A$54,F7,$D$5:$D$54,"Check qty")>0,"Fix lines","OK")))
A8: Spa Set | B8: Tissue paper sheet | C8: 2 | D8: =IF(B8="","",IF(NOT(ISNUMBER(C8)),"Check qty",IFERROR(ROUND(C8*INDEX(Parts!$B$5:$B$30,MATCH(B8,Parts!$A$5:$A$30,0)),2),"Missing part"))) | F8: Starter Trio | G8: =IF(F8="","",SUMIF($A$5:$A$54,F8,$D$5:$D$54)) | H8: 32 | I8: =IF(F8="","",IF(AND(ISNUMBER(H8),H8>0),(H8-G8)/H8,"")) | J8: =IF(F8="","",IF(ISNUMBER(H8),H8-G8,"")) | K8: =IF(F8="","",IF(COUNTIF($A$5:$A$54,F8)=0,"No lines",IF(COUNTIFS($A$5:$A$54,F8,$D$5:$D$54,"Missing part")+COUNTIFS($A$5:$A$54,F8,$D$5:$D$54,"Check qty")>0,"Fix lines","OK")))
A9: Spa Set | B9: Ribbon, 1 yd | C9: 1 | D9: =IF(B9="","",IF(NOT(ISNUMBER(C9)),"Check qty",IFERROR(ROUND(C9*INDEX(Parts!$B$5:$B$30,MATCH(B9,Parts!$A$5:$A$30,0)),2),"Missing part"))) | G9: =IF(F9="","",SUMIF($A$5:$A$54,F9,$D$5:$D$54)) | I9: =IF(F9="","",IF(AND(ISNUMBER(H9),H9>0),(H9-G9)/H9,"")) | J9: =IF(F9="","",IF(ISNUMBER(H9),H9-G9,"")) | K9: =IF(F9="","",IF(COUNTIF($A$5:$A$54,F9)=0,"No lines",IF(COUNTIFS($A$5:$A$54,F9,$D$5:$D$54,"Missing part")+COUNTIFS($A$5:$A$54,F9,$D$5:$D$54,"Check qty")>0,"Fix lines","OK")))
A10: Cozy Mug Set | B10: Enamel mug | C10: 1 | D10: =IF(B10="","",IF(NOT(ISNUMBER(C10)),"Check qty",IFERROR(ROUND(C10*INDEX(Parts!$B$5:$B$30,MATCH(B10,Parts!$A$5:$A$30,0)),2),"Missing part"))) | G10: =IF(F10="","",SUMIF($A$5:$A$54,F10,$D$5:$D$54)) | I10: =IF(F10="","",IF(AND(ISNUMBER(H10),H10>0),(H10-G10)/H10,"")) | J10: =IF(F10="","",IF(ISNUMBER(H10),H10-G10,"")) | K10: =IF(F10="","",IF(COUNTIF($A$5:$A$54,F10)=0,"No lines",IF(COUNTIFS($A$5:$A$54,F10,$D$5:$D$54,"Missing part")+COUNTIFS($A$5:$A$54,F10,$D$5:$D$54,"Check qty")>0,"Fix lines","OK")))
A11: Cozy Mug Set | B11: Tea sample tin | C11: 2 | D11: =IF(B11="","",IF(NOT(ISNUMBER(C11)),"Check qty",IFERROR(ROUND(C11*INDEX(Parts!$B$5:$B$30,MATCH(B11,Parts!$A$5:$A$30,0)),2),"Missing part")))
A12: Cozy Mug Set | B12: Gift box | C12: 1 | D12: =IF(B12="","",IF(NOT(ISNUMBER(C12)),"Check qty",IFERROR(ROUND(C12*INDEX(Parts!$B$5:$B$30,MATCH(B12,Parts!$A$5:$A$30,0)),2),"Missing part"))) | F12: CHECK | G12: =IF(AND(COUNTIF($D$5:$D$54,"Missing part")=0,COUNTIF($D$5:$D$54,"Check qty")=0,SUMPRODUCT((Parts!$A$5:$A$30<>"")*(COUNTIF(Parts!$A$5:$A$30,Parts!$A$5:$A$30)>1))=0,SUMPRODUCT(($B$5:$B$54<>"")*($A$5:$A$54=""))=0,ROUND(SUM($D$5:$D$54)-SUM($G$5:$G$10),2)=0,SUMPRODUCT(($F$5:$F$10<>"")*(1-ISNUMBER($H$5:$H$10)))=0),"OK","CHECK")
A13: Cozy Mug Set | B13: Tissue paper sheet | C13: 2 | D13: =IF(B13="","",IF(NOT(ISNUMBER(C13)),"Check qty",IFERROR(ROUND(C13*INDEX(Parts!$B$5:$B$30,MATCH(B13,Parts!$A$5:$A$30,0)),2),"Missing part")))
A14: Cozy Mug Set | B14: Ribbon, 1 yd | C14: 1 | D14: =IF(B14="","",IF(NOT(ISNUMBER(C14)),"Check qty",IFERROR(ROUND(C14*INDEX(Parts!$B$5:$B$30,MATCH(B14,Parts!$A$5:$A$30,0)),2),"Missing part")))
A15: Candle Duo | B15: Soy candle, 8 oz | C15: 2 | D15: =IF(B15="","",IF(NOT(ISNUMBER(C15)),"Check qty",IFERROR(ROUND(C15*INDEX(Parts!$B$5:$B$30,MATCH(B15,Parts!$A$5:$A$30,0)),2),"Missing part")))
A16: Candle Duo | B16: Gift box | C16: 1 | D16: =IF(B16="","",IF(NOT(ISNUMBER(C16)),"Check qty",IFERROR(ROUND(C16*INDEX(Parts!$B$5:$B$30,MATCH(B16,Parts!$A$5:$A$30,0)),2),"Missing part")))
A17: Candle Duo | B17: Tissue paper sheet | C17: 3 | D17: =IF(B17="","",IF(NOT(ISNUMBER(C17)),"Check qty",IFERROR(ROUND(C17*INDEX(Parts!$B$5:$B$30,MATCH(B17,Parts!$A$5:$A$30,0)),2),"Missing part")))
A18: Starter Trio | B18: Soap bar, oatmeal | C18: 1 | D18: =IF(B18="","",IF(NOT(ISNUMBER(C18)),"Check qty",IFERROR(ROUND(C18*INDEX(Parts!$B$5:$B$30,MATCH(B18,Parts!$A$5:$A$30,0)),2),"Missing part")))
A19: Starter Trio | B19: Soy candle, 8 oz | C19: 1 | D19: =IF(B19="","",IF(NOT(ISNUMBER(C19)),"Check qty",IFERROR(ROUND(C19*INDEX(Parts!$B$5:$B$30,MATCH(B19,Parts!$A$5:$A$30,0)),2),"Missing part")))
A20: Starter Trio | B20: Enamel mug | C20: 1 | D20: =IF(B20="","",IF(NOT(ISNUMBER(C20)),"Check qty",IFERROR(ROUND(C20*INDEX(Parts!$B$5:$B$30,MATCH(B20,Parts!$A$5:$A$30,0)),2),"Missing part")))
A21: Starter Trio | B21: Gift box | C21: 1 | D21: =IF(B21="","",IF(NOT(ISNUMBER(C21)),"Check qty",IFERROR(ROUND(C21*INDEX(Parts!$B$5:$B$30,MATCH(B21,Parts!$A$5:$A$30,0)),2),"Missing part")))
A22: Starter Trio | B22: Tissue paper sheet | C22: 3 | D22: =IF(B22="","",IF(NOT(ISNUMBER(C22)),"Check qty",IFERROR(ROUND(C22*INDEX(Parts!$B$5:$B$30,MATCH(B22,Parts!$A$5:$A$30,0)),2),"Missing part")))
A23: Starter Trio | B23: Ribbon, 1 yd | C23: 2 | D23: =IF(B23="","",IF(NOT(ISNUMBER(C23)),"Check qty",IFERROR(ROUND(C23*INDEX(Parts!$B$5:$B$30,MATCH(B23,Parts!$A$5:$A$30,0)),2),"Missing part")))
D24: =IF(B24="","",IF(NOT(ISNUMBER(C24)),"Check qty",IFERROR(ROUND(C24*INDEX(Parts!$B$5:$B$30,MATCH(B24,Parts!$A$5:$A$30,0)),2),"Missing part")))
D25: =IF(B25="","",IF(NOT(ISNUMBER(C25)),"Check qty",IFERROR(ROUND(C25*INDEX(Parts!$B$5:$B$30,MATCH(B25,Parts!$A$5:$A$30,0)),2),"Missing part")))
D26: =IF(B26="","",IF(NOT(ISNUMBER(C26)),"Check qty",IFERROR(ROUND(C26*INDEX(Parts!$B$5:$B$30,MATCH(B26,Parts!$A$5:$A$30,0)),2),"Missing part")))
D27: =IF(B27="","",IF(NOT(ISNUMBER(C27)),"Check qty",IFERROR(ROUND(C27*INDEX(Parts!$B$5:$B$30,MATCH(B27,Parts!$A$5:$A$30,0)),2),"Missing part")))
D28: =IF(B28="","",IF(NOT(ISNUMBER(C28)),"Check qty",IFERROR(ROUND(C28*INDEX(Parts!$B$5:$B$30,MATCH(B28,Parts!$A$5:$A$30,0)),2),"Missing part")))
D29: =IF(B29="","",IF(NOT(ISNUMBER(C29)),"Check qty",IFERROR(ROUND(C29*INDEX(Parts!$B$5:$B$30,MATCH(B29,Parts!$A$5:$A$30,0)),2),"Missing part")))
D30: =IF(B30="","",IF(NOT(ISNUMBER(C30)),"Check qty",IFERROR(ROUND(C30*INDEX(Parts!$B$5:$B$30,MATCH(B30,Parts!$A$5:$A$30,0)),2),"Missing part")))
D31: =IF(B31="","",IF(NOT(ISNUMBER(C31)),"Check qty",IFERROR(ROUND(C31*INDEX(Parts!$B$5:$B$30,MATCH(B31,Parts!$A$5:$A$30,0)),2),"Missing part")))
D32: =IF(B32="","",IF(NOT(ISNUMBER(C32)),"Check qty",IFERROR(ROUND(C32*INDEX(Parts!$B$5:$B$30,MATCH(B32,Parts!$A$5:$A$30,0)),2),"Missing part")))
D33: =IF(B33="","",IF(NOT(ISNUMBER(C33)),"Check qty",IFERROR(ROUND(C33*INDEX(Parts!$B$5:$B$30,MATCH(B33,Parts!$A$5:$A$30,0)),2),"Missing part")))
D34: =IF(B34="","",IF(NOT(ISNUMBER(C34)),"Check qty",IFERROR(ROUND(C34*INDEX(Parts!$B$5:$B$30,MATCH(B34,Parts!$A$5:$A$30,0)),2),"Missing part")))
D35: =IF(B35="","",IF(NOT(ISNUMBER(C35)),"Check qty",IFERROR(ROUND(C35*INDEX(Parts!$B$5:$B$30,MATCH(B35,Parts!$A$5:$A$30,0)),2),"Missing part")))
... D54: =IF(B54="","",IF(NOT(ISNUMBER(C54)),"Check qty",IFERROR(ROUND(C54*INDEX(Parts!$B$5:$B$30,MATCH(B54,Parts!$A$5:$A$30,0)),2),"Missing part")))

Sheet How to use
A1: Tidy Tabs: Cost and Margin of a Gift Set
A3: 1. Parts tab: each part once, with its unit cost, in A5:B30 (yellow). The parts and costs are fictional.
A4: 2. Sets tab, left side: one line per part in a set, A5:C54 (yellow): set name, part (spelled as on the Parts tab), quantity. The sample has 4 fictional sets.
A5: 3. Line cost, D5: =IF(B5="","",IF(NOT(ISNUMBER(C5)),"Check qty",IFERROR(ROUND(C5*INDEX(Parts!$B$5:$B$30,MATCH(B5,Parts!$A$5:$A$30,0)),2),"Missing part"))).
A6: 4. Sets tab, right side: set names in F5:F10 and selling prices in H5:H10 (yellow). Cost, G5: =SUMIF($A$5:$A$54,F5,$D$5:$D$54). Margin, I5: =(H5-G5)/H5. Profit, J5: =H5-G5.
A7: 5. Margin is profit as a share of the price. A quantity of 0 costs $0.00. A part spelled differently from the Parts tab shows Missing part and is left out of the set cost, so the cost looks too low until you fix it.
A8: 6. CHECK, G12, shows CHECK when any line says Missing part or Check qty, a part is listed twice on the Parts tab (the first one is used), a line has a part but no set name, a line's set is not in F5:F10, or a price is missing.
A9: 7. Costs here are only the parts you list: add labor, packaging and fees as parts if they belong. This is arithmetic, not pricing advice.
A11: Checked in LibreOffice Calc only; not opened in Excel or Google Sheets.
A12: Google Sheets: File > Import > Upload this .xlsx.
