Workbook

Sheet Items
A1: Expected money in and out. Type the date, a description, In or Out, and the amount as a positive number.
A2: Fictional freelancer and shop. Amounts are guesses, not a promise.
A4: Date | B4: Description | C4: Type | D4: Amount | E4: Row check
A5: 46328 | B5: Studio rent | C5: Out | D5: 650 | E5: =IF(AND(A5="",B5="",C5="",D5=""),"",IF(NOT(ISNUMBER(A5)),"Check date",IF(AND(C5<>"In",C5<>"Out"),"Check type",IF(NOT(ISNUMBER(D5)),"Check amount",IF(D5<0,"Check amount",IF(ISNUMBER(Forecast!$B$2),IF(OR(A5<Forecast!$B$2,A5>=Forecast!$B$2+91),"Outside weeks",""),""))))))
A6: 46330 | B6: Supplies order | C6: Out | D6: 320 | E6: =IF(AND(A6="",B6="",C6="",D6=""),"",IF(NOT(ISNUMBER(A6)),"Check date",IF(AND(C6<>"In",C6<>"Out"),"Check type",IF(NOT(ISNUMBER(D6)),"Check amount",IF(D6<0,"Check amount",IF(ISNUMBER(Forecast!$B$2),IF(OR(A6<Forecast!$B$2,A6>=Forecast!$B$2+91),"Outside weeks",""),""))))))
A7: 46332 | B7: Client invoice 2040 | C7: In | D7: 600 | E7: =IF(AND(A7="",B7="",C7="",D7=""),"",IF(NOT(ISNUMBER(A7)),"Check date",IF(AND(C7<>"In",C7<>"Out"),"Check type",IF(NOT(ISNUMBER(D7)),"Check amount",IF(D7<0,"Check amount",IF(ISNUMBER(Forecast!$B$2),IF(OR(A7<Forecast!$B$2,A7>=Forecast!$B$2+91),"Outside weeks",""),""))))))
A8: 46335 | B8: Etsy payout | C8: In | D8: 340 | E8: =IF(AND(A8="",B8="",C8="",D8=""),"",IF(NOT(ISNUMBER(A8)),"Check date",IF(AND(C8<>"In",C8<>"Out"),"Check type",IF(NOT(ISNUMBER(D8)),"Check amount",IF(D8<0,"Check amount",IF(ISNUMBER(Forecast!$B$2),IF(OR(A8<Forecast!$B$2,A8>=Forecast!$B$2+91),"Outside weeks",""),""))))))
A9: 46335 | B9: Software subscription | C9: Out | D9: 45 | E9: =IF(AND(A9="",B9="",C9="",D9=""),"",IF(NOT(ISNUMBER(A9)),"Check date",IF(AND(C9<>"In",C9<>"Out"),"Check type",IF(NOT(ISNUMBER(D9)),"Check amount",IF(D9<0,"Check amount",IF(ISNUMBER(Forecast!$B$2),IF(OR(A9<Forecast!$B$2,A9>=Forecast!$B$2+91),"Outside weeks",""),""))))))
A10: 46342 | B10: Insurance payment | C10: Out | D10: 210 | E10: =IF(AND(A10="",B10="",C10="",D10=""),"",IF(NOT(ISNUMBER(A10)),"Check date",IF(AND(C10<>"In",C10<>"Out"),"Check type",IF(NOT(ISNUMBER(D10)),"Check amount",IF(D10<0,"Check amount",IF(ISNUMBER(Forecast!$B$2),IF(OR(A10<Forecast!$B$2,A10>=Forecast!$B$2+91),"Outside weeks",""),""))))))
A11: 46345 | B11: Craft fair booth fee | C11: Out | D11: 180 | E11: =IF(AND(A11="",B11="",C11="",D11=""),"",IF(NOT(ISNUMBER(A11)),"Check date",IF(AND(C11<>"In",C11<>"Out"),"Check type",IF(NOT(ISNUMBER(D11)),"Check amount",IF(D11<0,"Check amount",IF(ISNUMBER(Forecast!$B$2),IF(OR(A11<Forecast!$B$2,A11>=Forecast!$B$2+91),"Outside weeks",""),""))))))
A12: 46346 | B12: Client invoice 2041 | C12: In | D12: 1800 | E12: =IF(AND(A12="",B12="",C12="",D12=""),"",IF(NOT(ISNUMBER(A12)),"Check date",IF(AND(C12<>"In",C12<>"Out"),"Check type",IF(NOT(ISNUMBER(D12)),"Check amount",IF(D12<0,"Check amount",IF(ISNUMBER(Forecast!$B$2),IF(OR(A12<Forecast!$B$2,A12>=Forecast!$B$2+91),"Outside weeks",""),""))))))
A13: 46349 | B13: Etsy payout | C13: In | D13: 410 | E13: =IF(AND(A13="",B13="",C13="",D13=""),"",IF(NOT(ISNUMBER(A13)),"Check date",IF(AND(C13<>"In",C13<>"Out"),"Check type",IF(NOT(ISNUMBER(D13)),"Check amount",IF(D13<0,"Check amount",IF(ISNUMBER(Forecast!$B$2),IF(OR(A13<Forecast!$B$2,A13>=Forecast!$B$2+91),"Outside weeks",""),""))))))
A14: 46351 | B14: Packaging and labels | C14: Out | D14: 260 | E14: =IF(AND(A14="",B14="",C14="",D14=""),"",IF(NOT(ISNUMBER(A14)),"Check date",IF(AND(C14<>"In",C14<>"Out"),"Check type",IF(NOT(ISNUMBER(D14)),"Check amount",IF(D14<0,"Check amount",IF(ISNUMBER(Forecast!$B$2),IF(OR(A14<Forecast!$B$2,A14>=Forecast!$B$2+91),"Outside weeks",""),""))))))
A15: 46356 | B15: Kiln repair | C15: Out | D15: 1275 | E15: =IF(AND(A15="",B15="",C15="",D15=""),"",IF(NOT(ISNUMBER(A15)),"Check date",IF(AND(C15<>"In",C15<>"Out"),"Check type",IF(NOT(ISNUMBER(D15)),"Check amount",IF(D15<0,"Check amount",IF(ISNUMBER(Forecast!$B$2),IF(OR(A15<Forecast!$B$2,A15>=Forecast!$B$2+91),"Outside weeks",""),""))))))
A16: 46358 | B16: Studio rent | C16: Out | D16: 650 | E16: =IF(AND(A16="",B16="",C16="",D16=""),"",IF(NOT(ISNUMBER(A16)),"Check date",IF(AND(C16<>"In",C16<>"Out"),"Check type",IF(NOT(ISNUMBER(D16)),"Check amount",IF(D16<0,"Check amount",IF(ISNUMBER(Forecast!$B$2),IF(OR(A16<Forecast!$B$2,A16>=Forecast!$B$2+91),"Outside weeks",""),""))))))
... A34: 46416 | B34: Etsy payout | C34: In | D34: 300 | E34: =IF(AND(A34="",B34="",C34="",D34=""),"",IF(NOT(ISNUMBER(A34)),"Check date",IF(AND(C34<>"In",C34<>"Out"),"Check type",IF(NOT(ISNUMBER(D34)),"Check amount",IF(D34<0,"Check amount",IF(ISNUMBER(Forecast!$B$2),IF(OR(A34<Forecast!$B$2,A34>=Forecast!$B$2+91),"Outside weeks",""),""))))))
E35: =IF(AND(A35="",B35="",C35="",D35=""),"",IF(NOT(ISNUMBER(A35)),"Check date",IF(AND(C35<>"In",C35<>"Out"),"Check type",IF(NOT(ISNUMBER(D35)),"Check amount",IF(D35<0,"Check amount",IF(ISNUMBER(Forecast!$B$2),IF(OR(A35<Forecast!$B$2,A35>=Forecast!$B$2+91),"Outside weeks",""),""))))))
E36: =IF(AND(A36="",B36="",C36="",D36=""),"",IF(NOT(ISNUMBER(A36)),"Check date",IF(AND(C36<>"In",C36<>"Out"),"Check type",IF(NOT(ISNUMBER(D36)),"Check amount",IF(D36<0,"Check amount",IF(ISNUMBER(Forecast!$B$2),IF(OR(A36<Forecast!$B$2,A36>=Forecast!$B$2+91),"Outside weeks",""),""))))))
E37: =IF(AND(A37="",B37="",C37="",D37=""),"",IF(NOT(ISNUMBER(A37)),"Check date",IF(AND(C37<>"In",C37<>"Out"),"Check type",IF(NOT(ISNUMBER(D37)),"Check amount",IF(D37<0,"Check amount",IF(ISNUMBER(Forecast!$B$2),IF(OR(A37<Forecast!$B$2,A37>=Forecast!$B$2+91),"Outside weeks",""),""))))))
E38: =IF(AND(A38="",B38="",C38="",D38=""),"",IF(NOT(ISNUMBER(A38)),"Check date",IF(AND(C38<>"In",C38<>"Out"),"Check type",IF(NOT(ISNUMBER(D38)),"Check amount",IF(D38<0,"Check amount",IF(ISNUMBER(Forecast!$B$2),IF(OR(A38<Forecast!$B$2,A38>=Forecast!$B$2+91),"Outside weeks",""),""))))))
E39: =IF(AND(A39="",B39="",C39="",D39=""),"",IF(NOT(ISNUMBER(A39)),"Check date",IF(AND(C39<>"In",C39<>"Out"),"Check type",IF(NOT(ISNUMBER(D39)),"Check amount",IF(D39<0,"Check amount",IF(ISNUMBER(Forecast!$B$2),IF(OR(A39<Forecast!$B$2,A39>=Forecast!$B$2+91),"Outside weeks",""),""))))))
E40: =IF(AND(A40="",B40="",C40="",D40=""),"",IF(NOT(ISNUMBER(A40)),"Check date",IF(AND(C40<>"In",C40<>"Out"),"Check type",IF(NOT(ISNUMBER(D40)),"Check amount",IF(D40<0,"Check amount",IF(ISNUMBER(Forecast!$B$2),IF(OR(A40<Forecast!$B$2,A40>=Forecast!$B$2+91),"Outside weeks",""),""))))))
E41: =IF(AND(A41="",B41="",C41="",D41=""),"",IF(NOT(ISNUMBER(A41)),"Check date",IF(AND(C41<>"In",C41<>"Out"),"Check type",IF(NOT(ISNUMBER(D41)),"Check amount",IF(D41<0,"Check amount",IF(ISNUMBER(Forecast!$B$2),IF(OR(A41<Forecast!$B$2,A41>=Forecast!$B$2+91),"Outside weeks",""),""))))))
E42: =IF(AND(A42="",B42="",C42="",D42=""),"",IF(NOT(ISNUMBER(A42)),"Check date",IF(AND(C42<>"In",C42<>"Out"),"Check type",IF(NOT(ISNUMBER(D42)),"Check amount",IF(D42<0,"Check amount",IF(ISNUMBER(Forecast!$B$2),IF(OR(A42<Forecast!$B$2,A42>=Forecast!$B$2+91),"Outside weeks",""),""))))))
E43: =IF(AND(A43="",B43="",C43="",D43=""),"",IF(NOT(ISNUMBER(A43)),"Check date",IF(AND(C43<>"In",C43<>"Out"),"Check type",IF(NOT(ISNUMBER(D43)),"Check amount",IF(D43<0,"Check amount",IF(ISNUMBER(Forecast!$B$2),IF(OR(A43<Forecast!$B$2,A43>=Forecast!$B$2+91),"Outside weeks",""),""))))))
E44: =IF(AND(A44="",B44="",C44="",D44=""),"",IF(NOT(ISNUMBER(A44)),"Check date",IF(AND(C44<>"In",C44<>"Out"),"Check type",IF(NOT(ISNUMBER(D44)),"Check amount",IF(D44<0,"Check amount",IF(ISNUMBER(Forecast!$B$2),IF(OR(A44<Forecast!$B$2,A44>=Forecast!$B$2+91),"Outside weeks",""),""))))))
E45: =IF(AND(A45="",B45="",C45="",D45=""),"",IF(NOT(ISNUMBER(A45)),"Check date",IF(AND(C45<>"In",C45<>"Out"),"Check type",IF(NOT(ISNUMBER(D45)),"Check amount",IF(D45<0,"Check amount",IF(ISNUMBER(Forecast!$B$2),IF(OR(A45<Forecast!$B$2,A45>=Forecast!$B$2+91),"Outside weeks",""),""))))))
E46: =IF(AND(A46="",B46="",C46="",D46=""),"",IF(NOT(ISNUMBER(A46)),"Check date",IF(AND(C46<>"In",C46<>"Out"),"Check type",IF(NOT(ISNUMBER(D46)),"Check amount",IF(D46<0,"Check amount",IF(ISNUMBER(Forecast!$B$2),IF(OR(A46<Forecast!$B$2,A46>=Forecast!$B$2+91),"Outside weeks",""),""))))))
... E104: =IF(AND(A104="",B104="",C104="",D104=""),"",IF(NOT(ISNUMBER(A104)),"Check date",IF(AND(C104<>"In",C104<>"Out"),"Check type",IF(NOT(ISNUMBER(D104)),"Check amount",IF(D104<0,"Check amount",IF(ISNUMBER(Forecast!$B$2),IF(OR(A104<Forecast!$B$2,A104>=Forecast!$B$2+91),"Outside weeks",""),""))))))

Sheet Forecast
A1: Opening balance | B1: 2400 | I1: Lowest ending balance | J1: =IF(COUNT(F6:F18)=0,"n/a",MIN(F6:F18))
A2: First Monday | B2: 46328 | C2: =IF(ISNUMBER(B2),TEXT(B2,"dddd"),"Type a date") | I2: Week that lowest balance begins | J2: =IF(COUNT(F6:F18)=0,"n/a",INDEX(A6:A18,MATCH(MIN(F6:F18),F6:F18,0)))
A3: Low-balance line | B3: 500 | I3: Weeks below the line | J3: =COUNTIF(G6:G18,"Below line")
A4: The low-balance line is a number you pick. It is not advice. | I4: Ending balance after week 13 | J4: =IF(ISNUMBER(F18),F18,"n/a")
A5: Week starts | B5: Week ends | C5: Money in | D5: Money out | E5: Net | F5: Ending balance | G5: Flag | I5: Items dated outside the 13 weeks | J5: =IF(ISNUMBER(B2),COUNTIFS(Items!$A$5:$A$104,"<"&B2)+COUNTIFS(Items!$A$5:$A$104,">="&B2+91),0)
A6: =IF(ISNUMBER($B$2),$B$2+7*(ROWS($A$6:A6)-1),"") | B6: =IF(A6="","",A6+6) | C6: =IF(A6="","",SUMIFS(Items!$D$5:$D$104,Items!$C$5:$C$104,"In",Items!$A$5:$A$104,">="&A6,Items!$A$5:$A$104,"<"&A6+7)) | D6: =IF(A6="","",SUMIFS(Items!$D$5:$D$104,Items!$C$5:$C$104,"Out",Items!$A$5:$A$104,">="&A6,Items!$A$5:$A$104,"<"&A6+7)) | E6: =IF(A6="","",ROUND(C6-D6,2)) | F6: =IF(OR(A6="",NOT(ISNUMBER($B$1))),"",ROUND(IF(ROWS($A$6:A6)=1,$B$1,F5)+E6,2)) | G6: =IF(OR(F6="",NOT(ISNUMBER($B$3))),"",IF(F6<$B$3,"Below line","")) | I6: Item rows to fix (date, type or amount) | J6: =SUMPRODUCT(--(LEFT(Items!$E$5:$E$104,5)="Check"))
A7: =IF(ISNUMBER($B$2),$B$2+7*(ROWS($A$6:A7)-1),"") | B7: =IF(A7="","",A7+6) | C7: =IF(A7="","",SUMIFS(Items!$D$5:$D$104,Items!$C$5:$C$104,"In",Items!$A$5:$A$104,">="&A7,Items!$A$5:$A$104,"<"&A7+7)) | D7: =IF(A7="","",SUMIFS(Items!$D$5:$D$104,Items!$C$5:$C$104,"Out",Items!$A$5:$A$104,">="&A7,Items!$A$5:$A$104,"<"&A7+7)) | E7: =IF(A7="","",ROUND(C7-D7,2)) | F7: =IF(OR(A7="",NOT(ISNUMBER($B$1))),"",ROUND(IF(ROWS($A$6:A7)=1,$B$1,F6)+E7,2)) | G7: =IF(OR(F7="",NOT(ISNUMBER($B$3))),"",IF(F7<$B$3,"Below line","")) | I7: Check: ending balance matches opening + in - out, nothing to fix | J7: =IF(NOT(AND(ISNUMBER(B1),ISNUMBER(B2),ISNUMBER(B3))),"Check",IF(AND(ROUND(B1+SUM(C6:C18)-SUM(D6:D18)-F18,2)=0,J5=0,J6=0,COUNTA(Items!A105:D500)=0),"OK","Check"))
A8: =IF(ISNUMBER($B$2),$B$2+7*(ROWS($A$6:A8)-1),"") | B8: =IF(A8="","",A8+6) | C8: =IF(A8="","",SUMIFS(Items!$D$5:$D$104,Items!$C$5:$C$104,"In",Items!$A$5:$A$104,">="&A8,Items!$A$5:$A$104,"<"&A8+7)) | D8: =IF(A8="","",SUMIFS(Items!$D$5:$D$104,Items!$C$5:$C$104,"Out",Items!$A$5:$A$104,">="&A8,Items!$A$5:$A$104,"<"&A8+7)) | E8: =IF(A8="","",ROUND(C8-D8,2)) | F8: =IF(OR(A8="",NOT(ISNUMBER($B$1))),"",ROUND(IF(ROWS($A$6:A8)=1,$B$1,F7)+E8,2)) | G8: =IF(OR(F8="",NOT(ISNUMBER($B$3))),"",IF(F8<$B$3,"Below line",""))
A9: =IF(ISNUMBER($B$2),$B$2+7*(ROWS($A$6:A9)-1),"") | B9: =IF(A9="","",A9+6) | C9: =IF(A9="","",SUMIFS(Items!$D$5:$D$104,Items!$C$5:$C$104,"In",Items!$A$5:$A$104,">="&A9,Items!$A$5:$A$104,"<"&A9+7)) | D9: =IF(A9="","",SUMIFS(Items!$D$5:$D$104,Items!$C$5:$C$104,"Out",Items!$A$5:$A$104,">="&A9,Items!$A$5:$A$104,"<"&A9+7)) | E9: =IF(A9="","",ROUND(C9-D9,2)) | F9: =IF(OR(A9="",NOT(ISNUMBER($B$1))),"",ROUND(IF(ROWS($A$6:A9)=1,$B$1,F8)+E9,2)) | G9: =IF(OR(F9="",NOT(ISNUMBER($B$3))),"",IF(F9<$B$3,"Below line",""))
A10: =IF(ISNUMBER($B$2),$B$2+7*(ROWS($A$6:A10)-1),"") | B10: =IF(A10="","",A10+6) | C10: =IF(A10="","",SUMIFS(Items!$D$5:$D$104,Items!$C$5:$C$104,"In",Items!$A$5:$A$104,">="&A10,Items!$A$5:$A$104,"<"&A10+7)) | D10: =IF(A10="","",SUMIFS(Items!$D$5:$D$104,Items!$C$5:$C$104,"Out",Items!$A$5:$A$104,">="&A10,Items!$A$5:$A$104,"<"&A10+7)) | E10: =IF(A10="","",ROUND(C10-D10,2)) | F10: =IF(OR(A10="",NOT(ISNUMBER($B$1))),"",ROUND(IF(ROWS($A$6:A10)=1,$B$1,F9)+E10,2)) | G10: =IF(OR(F10="",NOT(ISNUMBER($B$3))),"",IF(F10<$B$3,"Below line",""))
A11: =IF(ISNUMBER($B$2),$B$2+7*(ROWS($A$6:A11)-1),"") | B11: =IF(A11="","",A11+6) | C11: =IF(A11="","",SUMIFS(Items!$D$5:$D$104,Items!$C$5:$C$104,"In",Items!$A$5:$A$104,">="&A11,Items!$A$5:$A$104,"<"&A11+7)) | D11: =IF(A11="","",SUMIFS(Items!$D$5:$D$104,Items!$C$5:$C$104,"Out",Items!$A$5:$A$104,">="&A11,Items!$A$5:$A$104,"<"&A11+7)) | E11: =IF(A11="","",ROUND(C11-D11,2)) | F11: =IF(OR(A11="",NOT(ISNUMBER($B$1))),"",ROUND(IF(ROWS($A$6:A11)=1,$B$1,F10)+E11,2)) | G11: =IF(OR(F11="",NOT(ISNUMBER($B$3))),"",IF(F11<$B$3,"Below line",""))
A12: =IF(ISNUMBER($B$2),$B$2+7*(ROWS($A$6:A12)-1),"") | B12: =IF(A12="","",A12+6) | C12: =IF(A12="","",SUMIFS(Items!$D$5:$D$104,Items!$C$5:$C$104,"In",Items!$A$5:$A$104,">="&A12,Items!$A$5:$A$104,"<"&A12+7)) | D12: =IF(A12="","",SUMIFS(Items!$D$5:$D$104,Items!$C$5:$C$104,"Out",Items!$A$5:$A$104,">="&A12,Items!$A$5:$A$104,"<"&A12+7)) | E12: =IF(A12="","",ROUND(C12-D12,2)) | F12: =IF(OR(A12="",NOT(ISNUMBER($B$1))),"",ROUND(IF(ROWS($A$6:A12)=1,$B$1,F11)+E12,2)) | G12: =IF(OR(F12="",NOT(ISNUMBER($B$3))),"",IF(F12<$B$3,"Below line",""))
A13: =IF(ISNUMBER($B$2),$B$2+7*(ROWS($A$6:A13)-1),"") | B13: =IF(A13="","",A13+6) | C13: =IF(A13="","",SUMIFS(Items!$D$5:$D$104,Items!$C$5:$C$104,"In",Items!$A$5:$A$104,">="&A13,Items!$A$5:$A$104,"<"&A13+7)) | D13: =IF(A13="","",SUMIFS(Items!$D$5:$D$104,Items!$C$5:$C$104,"Out",Items!$A$5:$A$104,">="&A13,Items!$A$5:$A$104,"<"&A13+7)) | E13: =IF(A13="","",ROUND(C13-D13,2)) | F13: =IF(OR(A13="",NOT(ISNUMBER($B$1))),"",ROUND(IF(ROWS($A$6:A13)=1,$B$1,F12)+E13,2)) | G13: =IF(OR(F13="",NOT(ISNUMBER($B$3))),"",IF(F13<$B$3,"Below line",""))
A14: =IF(ISNUMBER($B$2),$B$2+7*(ROWS($A$6:A14)-1),"") | B14: =IF(A14="","",A14+6) | C14: =IF(A14="","",SUMIFS(Items!$D$5:$D$104,Items!$C$5:$C$104,"In",Items!$A$5:$A$104,">="&A14,Items!$A$5:$A$104,"<"&A14+7)) | D14: =IF(A14="","",SUMIFS(Items!$D$5:$D$104,Items!$C$5:$C$104,"Out",Items!$A$5:$A$104,">="&A14,Items!$A$5:$A$104,"<"&A14+7)) | E14: =IF(A14="","",ROUND(C14-D14,2)) | F14: =IF(OR(A14="",NOT(ISNUMBER($B$1))),"",ROUND(IF(ROWS($A$6:A14)=1,$B$1,F13)+E14,2)) | G14: =IF(OR(F14="",NOT(ISNUMBER($B$3))),"",IF(F14<$B$3,"Below line",""))
A15: =IF(ISNUMBER($B$2),$B$2+7*(ROWS($A$6:A15)-1),"") | B15: =IF(A15="","",A15+6) | C15: =IF(A15="","",SUMIFS(Items!$D$5:$D$104,Items!$C$5:$C$104,"In",Items!$A$5:$A$104,">="&A15,Items!$A$5:$A$104,"<"&A15+7)) | D15: =IF(A15="","",SUMIFS(Items!$D$5:$D$104,Items!$C$5:$C$104,"Out",Items!$A$5:$A$104,">="&A15,Items!$A$5:$A$104,"<"&A15+7)) | E15: =IF(A15="","",ROUND(C15-D15,2)) | F15: =IF(OR(A15="",NOT(ISNUMBER($B$1))),"",ROUND(IF(ROWS($A$6:A15)=1,$B$1,F14)+E15,2)) | G15: =IF(OR(F15="",NOT(ISNUMBER($B$3))),"",IF(F15<$B$3,"Below line",""))
A16: =IF(ISNUMBER($B$2),$B$2+7*(ROWS($A$6:A16)-1),"") | B16: =IF(A16="","",A16+6) | C16: =IF(A16="","",SUMIFS(Items!$D$5:$D$104,Items!$C$5:$C$104,"In",Items!$A$5:$A$104,">="&A16,Items!$A$5:$A$104,"<"&A16+7)) | D16: =IF(A16="","",SUMIFS(Items!$D$5:$D$104,Items!$C$5:$C$104,"Out",Items!$A$5:$A$104,">="&A16,Items!$A$5:$A$104,"<"&A16+7)) | E16: =IF(A16="","",ROUND(C16-D16,2)) | F16: =IF(OR(A16="",NOT(ISNUMBER($B$1))),"",ROUND(IF(ROWS($A$6:A16)=1,$B$1,F15)+E16,2)) | G16: =IF(OR(F16="",NOT(ISNUMBER($B$3))),"",IF(F16<$B$3,"Below line",""))
A17: =IF(ISNUMBER($B$2),$B$2+7*(ROWS($A$6:A17)-1),"") | B17: =IF(A17="","",A17+6) | C17: =IF(A17="","",SUMIFS(Items!$D$5:$D$104,Items!$C$5:$C$104,"In",Items!$A$5:$A$104,">="&A17,Items!$A$5:$A$104,"<"&A17+7)) | D17: =IF(A17="","",SUMIFS(Items!$D$5:$D$104,Items!$C$5:$C$104,"Out",Items!$A$5:$A$104,">="&A17,Items!$A$5:$A$104,"<"&A17+7)) | E17: =IF(A17="","",ROUND(C17-D17,2)) | F17: =IF(OR(A17="",NOT(ISNUMBER($B$1))),"",ROUND(IF(ROWS($A$6:A17)=1,$B$1,F16)+E17,2)) | G17: =IF(OR(F17="",NOT(ISNUMBER($B$3))),"",IF(F17<$B$3,"Below line",""))
A18: =IF(ISNUMBER($B$2),$B$2+7*(ROWS($A$6:A18)-1),"") | B18: =IF(A18="","",A18+6) | C18: =IF(A18="","",SUMIFS(Items!$D$5:$D$104,Items!$C$5:$C$104,"In",Items!$A$5:$A$104,">="&A18,Items!$A$5:$A$104,"<"&A18+7)) | D18: =IF(A18="","",SUMIFS(Items!$D$5:$D$104,Items!$C$5:$C$104,"Out",Items!$A$5:$A$104,">="&A18,Items!$A$5:$A$104,"<"&A18+7)) | E18: =IF(A18="","",ROUND(C18-D18,2)) | F18: =IF(OR(A18="",NOT(ISNUMBER($B$1))),"",ROUND(IF(ROWS($A$6:A18)=1,$B$1,F17)+E18,2)) | G18: =IF(OR(F18="",NOT(ISNUMBER($B$3))),"",IF(F18<$B$3,"Below line",""))
A19: Total | C19: =IF(COUNT(C6:C18)=0,"",ROUND(SUM(C6:C18),2)) | D19: =IF(COUNT(D6:D18)=0,"",ROUND(SUM(D6:D18),2)) | E19: =IF(COUNT(E6:E18)=0,"",ROUND(SUM(E6:E18),2))

Sheet How to use
A1: Tidy Tabs: Weekly Cash Flow Forecast with the Lowest Balance
A3: 1. Items tab: one row per expected payment in A5:D104 (yellow): date, description, Type (In or Out) and Amount. Type the amount as a positive number; the Type column says which way the money goes. The sample is 30 fictional items.
A4: 2. Forecast tab: type the opening balance in B1, the first Monday in B2 and a low-balance line in B3 (all yellow). The line is a number you choose, not advice. The sample uses $2,400.00, 11/02/2026 and $500.00. If B2 is not a Monday, the weeks still run 7 days from that date.
A5: 3. Week starts, A6: =IF(ISNUMBER($B$2),$B$2+7*(ROWS($A$6:A6)-1),""). ROWS counts 1, 2, 3 ... down the table, so each row starts 7 days after the one above. Week ends, B6: =A6+6.
A6: 4. Money in, C6: =SUMIFS(Items!$D$5:$D$104,Items!$C$5:$C$104,"In",Items!$A$5:$A$104,">="&A6,Items!$A$5:$A$104,"<"&A6+7). It adds amounts typed In whose date is on or after the week start and before the next week start, so every day belongs to exactly one week. Money out, D6, is the same with "Out".
A7: 5. Net, E6: =ROUND(C6-D6,2). Ending balance, F6: the opening balance (first row) or the row above, plus the week's net. The first row reads B1 directly, so the header text is never used. Flag, G6: Below line when the ending balance is under B3.
A8: 6. Summary, I1:J7: the lowest ending balance =MIN(F6:F18), the week it begins =INDEX(A6:A18,MATCH(MIN(F6:F18),F6:F18,0)) (the first week if two weeks tie), weeks below the line, the balance after week 13, items outside the 13 weeks, and item rows to fix.
A9: 7. Items column E (Row check) shows Check date, Check type, Check amount or Outside weeks. Check type means the Type cell is not exactly In or Out (capital letters do not matter, a trailing space does). A negative amount, a text amount and a text date show Check. An item outside the 13 weeks is not in any week.
A10: 8. J7 shows OK when the ending balance equals the opening balance plus total in minus total out, no item is outside the 13 weeks, no item row needs fixing and nothing is typed below row 104.
A11: 9. The forecast is only as good as the dates and amounts you type. It gives no financial, tax or lending advice.
A13: Dates, items and amounts are fictional. Checked in LibreOffice Calc only; not opened in Excel or Google Sheets.
A14: Google Sheets: File > Import > Upload this .xlsx.
