Workbook

Sheet Orders
A1: Fictional custom orders. Payments are on the Payments tab; the as-of date is on the Settings tab. Yellow cells are inputs, gray cells are formulas. | K1: Summary
K2: Orders listed | L2: =COUNTA(A5:A64)
K3: Total ordered | L3: =SUM(D5:D64)
A4: Order # | B4: Customer | C4: Item | D4: Order total | E4: Due date | F4: Paid so far | G4: Balance due | H4: Status | I4: Deposit percent | K4: Total received | L4: =SUM(F5:F64)
A5: CO-1001 | B5: Hana Ortiz | C5: Wedding sign, cedar | D5: 480 | E5: 46346 | F5: =IF(A5="","",SUMIF(Payments!$A$5:$A$104,A5,Payments!$C$5:$C$104)) | G5: =IF(A5="","",IF(ISNUMBER(D5),ROUND(D5-F5,2),"")) | H5: =IF(A5="","",IF(Settings!$B$2<>"OK","Check settings",IF(NOT(ISNUMBER(D5)),"Check total",IF(G5<0,"Overpaid",IF(G5=0,"Paid in full",IF(F5=0,IF(AND(ISNUMBER(E5),E5<Settings!$B$1),"Past due","Awaiting deposit"),IF(AND(ISNUMBER(E5),E5<Settings!$B$1),"Past due","Deposit received"))))))) | I5: =IF(A5="","",IF(ISNUMBER(D5),IF(D5=0,"",ROUND(F5/D5,4)),"")) | K5: Total balance due (overpaid orders count as negative) | L5: =ROUND(SUM(G5:G64),2)
A6: CO-1002 | B6: Marcus Bell | C6: Cake topper set | D6: 85 | E6: 46319 | F6: =IF(A6="","",SUMIF(Payments!$A$5:$A$104,A6,Payments!$C$5:$C$104)) | G6: =IF(A6="","",IF(ISNUMBER(D6),ROUND(D6-F6,2),"")) | H6: =IF(A6="","",IF(Settings!$B$2<>"OK","Check settings",IF(NOT(ISNUMBER(D6)),"Check total",IF(G6<0,"Overpaid",IF(G6=0,"Paid in full",IF(F6=0,IF(AND(ISNUMBER(E6),E6<Settings!$B$1),"Past due","Awaiting deposit"),IF(AND(ISNUMBER(E6),E6<Settings!$B$1),"Past due","Deposit received"))))))) | I6: =IF(A6="","",IF(ISNUMBER(D6),IF(D6=0,"",ROUND(F6/D6,4)),"")) | K6: Past due orders | L6: =COUNTIF(H5:H64,"Past due")
A7: CO-1003 | B7: Priya Nair | C7: Embroidered tote x 12 | D7: 200 | E7: 46324 | F7: =IF(A7="","",SUMIF(Payments!$A$5:$A$104,A7,Payments!$C$5:$C$104)) | G7: =IF(A7="","",IF(ISNUMBER(D7),ROUND(D7-F7,2),"")) | H7: =IF(A7="","",IF(Settings!$B$2<>"OK","Check settings",IF(NOT(ISNUMBER(D7)),"Check total",IF(G7<0,"Overpaid",IF(G7=0,"Paid in full",IF(F7=0,IF(AND(ISNUMBER(E7),E7<Settings!$B$1),"Past due","Awaiting deposit"),IF(AND(ISNUMBER(E7),E7<Settings!$B$1),"Past due","Deposit received"))))))) | I7: =IF(A7="","",IF(ISNUMBER(D7),IF(D7=0,"",ROUND(F7/D7,4)),"")) | K7: Past due balance | L7: =SUMIF(H5:H64,"Past due",G5:G64)
A8: CO-1004 | B8: Lena Fischer | C8: Custom pet portrait | D8: 120 | E8: 46334 | F8: =IF(A8="","",SUMIF(Payments!$A$5:$A$104,A8,Payments!$C$5:$C$104)) | G8: =IF(A8="","",IF(ISNUMBER(D8),ROUND(D8-F8,2),"")) | H8: =IF(A8="","",IF(Settings!$B$2<>"OK","Check settings",IF(NOT(ISNUMBER(D8)),"Check total",IF(G8<0,"Overpaid",IF(G8=0,"Paid in full",IF(F8=0,IF(AND(ISNUMBER(E8),E8<Settings!$B$1),"Past due","Awaiting deposit"),IF(AND(ISNUMBER(E8),E8<Settings!$B$1),"Past due","Deposit received"))))))) | I8: =IF(A8="","",IF(ISNUMBER(D8),IF(D8=0,"",ROUND(F8/D8,4)),"")) | K8: Payments with no matching order or a text amount | L8: =COUNTIF(Payments!$E$5:$E$104,"No order")+COUNTIF(Payments!$E$5:$E$104,"Check amount")
A9: CO-1005 | B9: Tom Reyes | C9: Monogram blanket | D9: 95 | E9: 46326 | F9: =IF(A9="","",SUMIF(Payments!$A$5:$A$104,A9,Payments!$C$5:$C$104)) | G9: =IF(A9="","",IF(ISNUMBER(D9),ROUND(D9-F9,2),"")) | H9: =IF(A9="","",IF(Settings!$B$2<>"OK","Check settings",IF(NOT(ISNUMBER(D9)),"Check total",IF(G9<0,"Overpaid",IF(G9=0,"Paid in full",IF(F9=0,IF(AND(ISNUMBER(E9),E9<Settings!$B$1),"Past due","Awaiting deposit"),IF(AND(ISNUMBER(E9),E9<Settings!$B$1),"Past due","Deposit received"))))))) | I9: =IF(A9="","",IF(ISNUMBER(D9),IF(D9=0,"",ROUND(F9/D9,4)),"")) | K9: Orders whose order # is listed twice | L9: =SUMPRODUCT((A5:A64<>"")*(COUNTIF(A5:A64,A5:A64)>1))
A10: CO-1006 | B10: Dana Kim | C10: Engraved cutting board | D10: 75 | E10: 46315 | F10: =IF(A10="","",SUMIF(Payments!$A$5:$A$104,A10,Payments!$C$5:$C$104)) | G10: =IF(A10="","",IF(ISNUMBER(D10),ROUND(D10-F10,2),"")) | H10: =IF(A10="","",IF(Settings!$B$2<>"OK","Check settings",IF(NOT(ISNUMBER(D10)),"Check total",IF(G10<0,"Overpaid",IF(G10=0,"Paid in full",IF(F10=0,IF(AND(ISNUMBER(E10),E10<Settings!$B$1),"Past due","Awaiting deposit"),IF(AND(ISNUMBER(E10),E10<Settings!$B$1),"Past due","Deposit received"))))))) | I10: =IF(A10="","",IF(ISNUMBER(D10),IF(D10=0,"",ROUND(F10/D10,4)),"")) | K10: Orders with a missing or text total | L10: =COUNTIF(H5:H64,"Check total")
A11: CO-1007 | B11: Chloe Burns | C11: Birthday banner set | D11: 45 | E11: 46323 | F11: =IF(A11="","",SUMIF(Payments!$A$5:$A$104,A11,Payments!$C$5:$C$104)) | G11: =IF(A11="","",IF(ISNUMBER(D11),ROUND(D11-F11,2),"")) | H11: =IF(A11="","",IF(Settings!$B$2<>"OK","Check settings",IF(NOT(ISNUMBER(D11)),"Check total",IF(G11<0,"Overpaid",IF(G11=0,"Paid in full",IF(F11=0,IF(AND(ISNUMBER(E11),E11<Settings!$B$1),"Past due","Awaiting deposit"),IF(AND(ISNUMBER(E11),E11<Settings!$B$1),"Past due","Deposit received"))))))) | I11: =IF(A11="","",IF(ISNUMBER(D11),IF(D11=0,"",ROUND(F11/D11,4)),"")) | K11: Check: ordered - received = balance due, every payment has an order | L11: =IF(AND(Settings!B2="OK",ROUND(L3-L4-L5,2)=0,L8=0,L9=0,L10=0),"OK","CHECK")
A12: CO-1008 | B12: Omar Haddad | C12: Ceramic mug set x 6 | D12: 180 | E12: 46338 | F12: =IF(A12="","",SUMIF(Payments!$A$5:$A$104,A12,Payments!$C$5:$C$104)) | G12: =IF(A12="","",IF(ISNUMBER(D12),ROUND(D12-F12,2),"")) | H12: =IF(A12="","",IF(Settings!$B$2<>"OK","Check settings",IF(NOT(ISNUMBER(D12)),"Check total",IF(G12<0,"Overpaid",IF(G12=0,"Paid in full",IF(F12=0,IF(AND(ISNUMBER(E12),E12<Settings!$B$1),"Past due","Awaiting deposit"),IF(AND(ISNUMBER(E12),E12<Settings!$B$1),"Past due","Deposit received"))))))) | I12: =IF(A12="","",IF(ISNUMBER(D12),IF(D12=0,"",ROUND(F12/D12,4)),""))
A13: CO-1009 | B13: Ruth Gold | C13: Table runner, linen | D13: 130 | E13: 46329 | F13: =IF(A13="","",SUMIF(Payments!$A$5:$A$104,A13,Payments!$C$5:$C$104)) | G13: =IF(A13="","",IF(ISNUMBER(D13),ROUND(D13-F13,2),"")) | H13: =IF(A13="","",IF(Settings!$B$2<>"OK","Check settings",IF(NOT(ISNUMBER(D13)),"Check total",IF(G13<0,"Overpaid",IF(G13=0,"Paid in full",IF(F13=0,IF(AND(ISNUMBER(E13),E13<Settings!$B$1),"Past due","Awaiting deposit"),IF(AND(ISNUMBER(E13),E13<Settings!$B$1),"Past due","Deposit received"))))))) | I13: =IF(A13="","",IF(ISNUMBER(D13),IF(D13=0,"",ROUND(F13/D13,4)),""))
A14: CO-1010 | B14: Jenna Wu | C14: Crochet baby blanket | D14: 160 | E14: 46357 | F14: =IF(A14="","",SUMIF(Payments!$A$5:$A$104,A14,Payments!$C$5:$C$104)) | G14: =IF(A14="","",IF(ISNUMBER(D14),ROUND(D14-F14,2),"")) | H14: =IF(A14="","",IF(Settings!$B$2<>"OK","Check settings",IF(NOT(ISNUMBER(D14)),"Check total",IF(G14<0,"Overpaid",IF(G14=0,"Paid in full",IF(F14=0,IF(AND(ISNUMBER(E14),E14<Settings!$B$1),"Past due","Awaiting deposit"),IF(AND(ISNUMBER(E14),E14<Settings!$B$1),"Past due","Deposit received"))))))) | I14: =IF(A14="","",IF(ISNUMBER(D14),IF(D14=0,"",ROUND(F14/D14,4)),""))
A15: CO-1011 | B15: Sam Alvarez | C15: Hand-lettered menu board | D15: 220 | E15: 46310 | F15: =IF(A15="","",SUMIF(Payments!$A$5:$A$104,A15,Payments!$C$5:$C$104)) | G15: =IF(A15="","",IF(ISNUMBER(D15),ROUND(D15-F15,2),"")) | H15: =IF(A15="","",IF(Settings!$B$2<>"OK","Check settings",IF(NOT(ISNUMBER(D15)),"Check total",IF(G15<0,"Overpaid",IF(G15=0,"Paid in full",IF(F15=0,IF(AND(ISNUMBER(E15),E15<Settings!$B$1),"Past due","Awaiting deposit"),IF(AND(ISNUMBER(E15),E15<Settings!$B$1),"Past due","Deposit received"))))))) | I15: =IF(A15="","",IF(ISNUMBER(D15),IF(D15=0,"",ROUND(F15/D15,4)),""))
A16: CO-1012 | B16: Nia Brooks | C16: Leather key fobs x 10 | D16: 90 | E16: 46331 | F16: =IF(A16="","",SUMIF(Payments!$A$5:$A$104,A16,Payments!$C$5:$C$104)) | G16: =IF(A16="","",IF(ISNUMBER(D16),ROUND(D16-F16,2),"")) | H16: =IF(A16="","",IF(Settings!$B$2<>"OK","Check settings",IF(NOT(ISNUMBER(D16)),"Check total",IF(G16<0,"Overpaid",IF(G16=0,"Paid in full",IF(F16=0,IF(AND(ISNUMBER(E16),E16<Settings!$B$1),"Past due","Awaiting deposit"),IF(AND(ISNUMBER(E16),E16<Settings!$B$1),"Past due","Deposit received"))))))) | I16: =IF(A16="","",IF(ISNUMBER(D16),IF(D16=0,"",ROUND(F16/D16,4)),""))
F17: =IF(A17="","",SUMIF(Payments!$A$5:$A$104,A17,Payments!$C$5:$C$104)) | G17: =IF(A17="","",IF(ISNUMBER(D17),ROUND(D17-F17,2),"")) | H17: =IF(A17="","",IF(Settings!$B$2<>"OK","Check settings",IF(NOT(ISNUMBER(D17)),"Check total",IF(G17<0,"Overpaid",IF(G17=0,"Paid in full",IF(F17=0,IF(AND(ISNUMBER(E17),E17<Settings!$B$1),"Past due","Awaiting deposit"),IF(AND(ISNUMBER(E17),E17<Settings!$B$1),"Past due","Deposit received"))))))) | I17: =IF(A17="","",IF(ISNUMBER(D17),IF(D17=0,"",ROUND(F17/D17,4)),""))
F18: =IF(A18="","",SUMIF(Payments!$A$5:$A$104,A18,Payments!$C$5:$C$104)) | G18: =IF(A18="","",IF(ISNUMBER(D18),ROUND(D18-F18,2),"")) | H18: =IF(A18="","",IF(Settings!$B$2<>"OK","Check settings",IF(NOT(ISNUMBER(D18)),"Check total",IF(G18<0,"Overpaid",IF(G18=0,"Paid in full",IF(F18=0,IF(AND(ISNUMBER(E18),E18<Settings!$B$1),"Past due","Awaiting deposit"),IF(AND(ISNUMBER(E18),E18<Settings!$B$1),"Past due","Deposit received"))))))) | I18: =IF(A18="","",IF(ISNUMBER(D18),IF(D18=0,"",ROUND(F18/D18,4)),""))
F19: =IF(A19="","",SUMIF(Payments!$A$5:$A$104,A19,Payments!$C$5:$C$104)) | G19: =IF(A19="","",IF(ISNUMBER(D19),ROUND(D19-F19,2),"")) | H19: =IF(A19="","",IF(Settings!$B$2<>"OK","Check settings",IF(NOT(ISNUMBER(D19)),"Check total",IF(G19<0,"Overpaid",IF(G19=0,"Paid in full",IF(F19=0,IF(AND(ISNUMBER(E19),E19<Settings!$B$1),"Past due","Awaiting deposit"),IF(AND(ISNUMBER(E19),E19<Settings!$B$1),"Past due","Deposit received"))))))) | I19: =IF(A19="","",IF(ISNUMBER(D19),IF(D19=0,"",ROUND(F19/D19,4)),""))
F20: =IF(A20="","",SUMIF(Payments!$A$5:$A$104,A20,Payments!$C$5:$C$104)) | G20: =IF(A20="","",IF(ISNUMBER(D20),ROUND(D20-F20,2),"")) | H20: =IF(A20="","",IF(Settings!$B$2<>"OK","Check settings",IF(NOT(ISNUMBER(D20)),"Check total",IF(G20<0,"Overpaid",IF(G20=0,"Paid in full",IF(F20=0,IF(AND(ISNUMBER(E20),E20<Settings!$B$1),"Past due","Awaiting deposit"),IF(AND(ISNUMBER(E20),E20<Settings!$B$1),"Past due","Deposit received"))))))) | I20: =IF(A20="","",IF(ISNUMBER(D20),IF(D20=0,"",ROUND(F20/D20,4)),""))
F21: =IF(A21="","",SUMIF(Payments!$A$5:$A$104,A21,Payments!$C$5:$C$104)) | G21: =IF(A21="","",IF(ISNUMBER(D21),ROUND(D21-F21,2),"")) | H21: =IF(A21="","",IF(Settings!$B$2<>"OK","Check settings",IF(NOT(ISNUMBER(D21)),"Check total",IF(G21<0,"Overpaid",IF(G21=0,"Paid in full",IF(F21=0,IF(AND(ISNUMBER(E21),E21<Settings!$B$1),"Past due","Awaiting deposit"),IF(AND(ISNUMBER(E21),E21<Settings!$B$1),"Past due","Deposit received"))))))) | I21: =IF(A21="","",IF(ISNUMBER(D21),IF(D21=0,"",ROUND(F21/D21,4)),""))
F22: =IF(A22="","",SUMIF(Payments!$A$5:$A$104,A22,Payments!$C$5:$C$104)) | G22: =IF(A22="","",IF(ISNUMBER(D22),ROUND(D22-F22,2),"")) | H22: =IF(A22="","",IF(Settings!$B$2<>"OK","Check settings",IF(NOT(ISNUMBER(D22)),"Check total",IF(G22<0,"Overpaid",IF(G22=0,"Paid in full",IF(F22=0,IF(AND(ISNUMBER(E22),E22<Settings!$B$1),"Past due","Awaiting deposit"),IF(AND(ISNUMBER(E22),E22<Settings!$B$1),"Past due","Deposit received"))))))) | I22: =IF(A22="","",IF(ISNUMBER(D22),IF(D22=0,"",ROUND(F22/D22,4)),""))
F23: =IF(A23="","",SUMIF(Payments!$A$5:$A$104,A23,Payments!$C$5:$C$104)) | G23: =IF(A23="","",IF(ISNUMBER(D23),ROUND(D23-F23,2),"")) | H23: =IF(A23="","",IF(Settings!$B$2<>"OK","Check settings",IF(NOT(ISNUMBER(D23)),"Check total",IF(G23<0,"Overpaid",IF(G23=0,"Paid in full",IF(F23=0,IF(AND(ISNUMBER(E23),E23<Settings!$B$1),"Past due","Awaiting deposit"),IF(AND(ISNUMBER(E23),E23<Settings!$B$1),"Past due","Deposit received"))))))) | I23: =IF(A23="","",IF(ISNUMBER(D23),IF(D23=0,"",ROUND(F23/D23,4)),""))
F24: =IF(A24="","",SUMIF(Payments!$A$5:$A$104,A24,Payments!$C$5:$C$104)) | G24: =IF(A24="","",IF(ISNUMBER(D24),ROUND(D24-F24,2),"")) | H24: =IF(A24="","",IF(Settings!$B$2<>"OK","Check settings",IF(NOT(ISNUMBER(D24)),"Check total",IF(G24<0,"Overpaid",IF(G24=0,"Paid in full",IF(F24=0,IF(AND(ISNUMBER(E24),E24<Settings!$B$1),"Past due","Awaiting deposit"),IF(AND(ISNUMBER(E24),E24<Settings!$B$1),"Past due","Deposit received"))))))) | I24: =IF(A24="","",IF(ISNUMBER(D24),IF(D24=0,"",ROUND(F24/D24,4)),""))
F25: =IF(A25="","",SUMIF(Payments!$A$5:$A$104,A25,Payments!$C$5:$C$104)) | G25: =IF(A25="","",IF(ISNUMBER(D25),ROUND(D25-F25,2),"")) | H25: =IF(A25="","",IF(Settings!$B$2<>"OK","Check settings",IF(NOT(ISNUMBER(D25)),"Check total",IF(G25<0,"Overpaid",IF(G25=0,"Paid in full",IF(F25=0,IF(AND(ISNUMBER(E25),E25<Settings!$B$1),"Past due","Awaiting deposit"),IF(AND(ISNUMBER(E25),E25<Settings!$B$1),"Past due","Deposit received"))))))) | I25: =IF(A25="","",IF(ISNUMBER(D25),IF(D25=0,"",ROUND(F25/D25,4)),""))
F26: =IF(A26="","",SUMIF(Payments!$A$5:$A$104,A26,Payments!$C$5:$C$104)) | G26: =IF(A26="","",IF(ISNUMBER(D26),ROUND(D26-F26,2),"")) | H26: =IF(A26="","",IF(Settings!$B$2<>"OK","Check settings",IF(NOT(ISNUMBER(D26)),"Check total",IF(G26<0,"Overpaid",IF(G26=0,"Paid in full",IF(F26=0,IF(AND(ISNUMBER(E26),E26<Settings!$B$1),"Past due","Awaiting deposit"),IF(AND(ISNUMBER(E26),E26<Settings!$B$1),"Past due","Deposit received"))))))) | I26: =IF(A26="","",IF(ISNUMBER(D26),IF(D26=0,"",ROUND(F26/D26,4)),""))
F27: =IF(A27="","",SUMIF(Payments!$A$5:$A$104,A27,Payments!$C$5:$C$104)) | G27: =IF(A27="","",IF(ISNUMBER(D27),ROUND(D27-F27,2),"")) | H27: =IF(A27="","",IF(Settings!$B$2<>"OK","Check settings",IF(NOT(ISNUMBER(D27)),"Check total",IF(G27<0,"Overpaid",IF(G27=0,"Paid in full",IF(F27=0,IF(AND(ISNUMBER(E27),E27<Settings!$B$1),"Past due","Awaiting deposit"),IF(AND(ISNUMBER(E27),E27<Settings!$B$1),"Past due","Deposit received"))))))) | I27: =IF(A27="","",IF(ISNUMBER(D27),IF(D27=0,"",ROUND(F27/D27,4)),""))
F28: =IF(A28="","",SUMIF(Payments!$A$5:$A$104,A28,Payments!$C$5:$C$104)) | G28: =IF(A28="","",IF(ISNUMBER(D28),ROUND(D28-F28,2),"")) | H28: =IF(A28="","",IF(Settings!$B$2<>"OK","Check settings",IF(NOT(ISNUMBER(D28)),"Check total",IF(G28<0,"Overpaid",IF(G28=0,"Paid in full",IF(F28=0,IF(AND(ISNUMBER(E28),E28<Settings!$B$1),"Past due","Awaiting deposit"),IF(AND(ISNUMBER(E28),E28<Settings!$B$1),"Past due","Deposit received"))))))) | I28: =IF(A28="","",IF(ISNUMBER(D28),IF(D28=0,"",ROUND(F28/D28,4)),""))
... F64: =IF(A64="","",SUMIF(Payments!$A$5:$A$104,A64,Payments!$C$5:$C$104)) | G64: =IF(A64="","",IF(ISNUMBER(D64),ROUND(D64-F64,2),"")) | H64: =IF(A64="","",IF(Settings!$B$2<>"OK","Check settings",IF(NOT(ISNUMBER(D64)),"Check total",IF(G64<0,"Overpaid",IF(G64=0,"Paid in full",IF(F64=0,IF(AND(ISNUMBER(E64),E64<Settings!$B$1),"Past due","Awaiting deposit"),IF(AND(ISNUMBER(E64),E64<Settings!$B$1),"Past due","Deposit received"))))))) | I64: =IF(A64="","",IF(ISNUMBER(D64),IF(D64=0,"",ROUND(F64/D64,4)),""))

Sheet Payments
A1: One row per payment. Type the order number exactly as it is on the Orders tab. Amount must be a number.
A4: Order # | B4: Date | C4: Amount | D4: Method | E4: Check
A5: CO-1002 | B5: 46279 | C5: 25 | D5: Cash | E5: =IF(AND(A5="",C5=""),"",IF(A5="","No order",IF(COUNTIF(Orders!$A$5:$A$64,A5)=0,"No order",IF(ISNUMBER(C5),"","Check amount"))))
A6: CO-1011 | B6: 46285 | C6: 60 | D6: Venmo | E6: =IF(AND(A6="",C6=""),"",IF(A6="","No order",IF(COUNTIF(Orders!$A$5:$A$64,A6)=0,"No order",IF(ISNUMBER(C6),"","Check amount"))))
A7: CO-1001 | B7: 46287 | C7: 80 | D7: Card | E7: =IF(AND(A7="",C7=""),"",IF(A7="","No order",IF(COUNTIF(Orders!$A$5:$A$64,A7)=0,"No order",IF(ISNUMBER(C7),"","Check amount"))))
A8: CO-1007 | B8: 46290 | C8: 20 | D8: Cash | E8: =IF(AND(A8="",C8=""),"",IF(A8="","No order",IF(COUNTIF(Orders!$A$5:$A$64,A8)=0,"No order",IF(ISNUMBER(C8),"","Check amount"))))
A9: CO-1003 | B9: 46300 | C9: 60 | D9: Venmo | E9: =IF(AND(A9="",C9=""),"",IF(A9="","No order",IF(COUNTIF(Orders!$A$5:$A$64,A9)=0,"No order",IF(ISNUMBER(C9),"","Check amount"))))
A10: CO-1008 | B10: 46301 | C10: 50 | D10: Card | E10: =IF(AND(A10="",C10=""),"",IF(A10="","No order",IF(COUNTIF(Orders!$A$5:$A$64,A10)=0,"No order",IF(ISNUMBER(C10),"","Check amount"))))
A11: CO-1009 | B11: 46302 | C11: 65 | D11: Check | E11: =IF(AND(A11="",C11=""),"",IF(A11="","No order",IF(COUNTIF(Orders!$A$5:$A$64,A11)=0,"No order",IF(ISNUMBER(C11),"","Check amount"))))
A12: CO-1012 | B12: 46304 | C12: 15 | D12: Venmo | E12: =IF(AND(A12="",C12=""),"",IF(A12="","No order",IF(COUNTIF(Orders!$A$5:$A$64,A12)=0,"No order",IF(ISNUMBER(C12),"","Check amount"))))
A13: CO-1010 | B13: 46305 | C13: 20 | D13: Card | E13: =IF(AND(A13="",C13=""),"",IF(A13="","No order",IF(COUNTIF(Orders!$A$5:$A$64,A13)=0,"No order",IF(ISNUMBER(C13),"","Check amount"))))
A14: CO-1002 | B14: 46307 | C14: 15 | D14: Cash | E14: =IF(AND(A14="",C14=""),"",IF(A14="","No order",IF(COUNTIF(Orders!$A$5:$A$64,A14)=0,"No order",IF(ISNUMBER(C14),"","Check amount"))))
A15: CO-1001 | B15: 46309 | C15: 70 | D15: Check | E15: =IF(AND(A15="",C15=""),"",IF(A15="","No order",IF(COUNTIF(Orders!$A$5:$A$64,A15)=0,"No order",IF(ISNUMBER(C15),"","Check amount"))))
A16: CO-1008 | B16: 46310 | C16: 50 | D16: Card | E16: =IF(AND(A16="",C16=""),"",IF(A16="","No order",IF(COUNTIF(Orders!$A$5:$A$64,A16)=0,"No order",IF(ISNUMBER(C16),"","Check amount"))))
... A24: CO-1010 | B24: 46325 | C24: 20 | D24: Card | E24: =IF(AND(A24="",C24=""),"",IF(A24="","No order",IF(COUNTIF(Orders!$A$5:$A$64,A24)=0,"No order",IF(ISNUMBER(C24),"","Check amount"))))
E25: =IF(AND(A25="",C25=""),"",IF(A25="","No order",IF(COUNTIF(Orders!$A$5:$A$64,A25)=0,"No order",IF(ISNUMBER(C25),"","Check amount"))))
E26: =IF(AND(A26="",C26=""),"",IF(A26="","No order",IF(COUNTIF(Orders!$A$5:$A$64,A26)=0,"No order",IF(ISNUMBER(C26),"","Check amount"))))
E27: =IF(AND(A27="",C27=""),"",IF(A27="","No order",IF(COUNTIF(Orders!$A$5:$A$64,A27)=0,"No order",IF(ISNUMBER(C27),"","Check amount"))))
E28: =IF(AND(A28="",C28=""),"",IF(A28="","No order",IF(COUNTIF(Orders!$A$5:$A$64,A28)=0,"No order",IF(ISNUMBER(C28),"","Check amount"))))
E29: =IF(AND(A29="",C29=""),"",IF(A29="","No order",IF(COUNTIF(Orders!$A$5:$A$64,A29)=0,"No order",IF(ISNUMBER(C29),"","Check amount"))))
E30: =IF(AND(A30="",C30=""),"",IF(A30="","No order",IF(COUNTIF(Orders!$A$5:$A$64,A30)=0,"No order",IF(ISNUMBER(C30),"","Check amount"))))
E31: =IF(AND(A31="",C31=""),"",IF(A31="","No order",IF(COUNTIF(Orders!$A$5:$A$64,A31)=0,"No order",IF(ISNUMBER(C31),"","Check amount"))))
E32: =IF(AND(A32="",C32=""),"",IF(A32="","No order",IF(COUNTIF(Orders!$A$5:$A$64,A32)=0,"No order",IF(ISNUMBER(C32),"","Check amount"))))
E33: =IF(AND(A33="",C33=""),"",IF(A33="","No order",IF(COUNTIF(Orders!$A$5:$A$64,A33)=0,"No order",IF(ISNUMBER(C33),"","Check amount"))))
E34: =IF(AND(A34="",C34=""),"",IF(A34="","No order",IF(COUNTIF(Orders!$A$5:$A$64,A34)=0,"No order",IF(ISNUMBER(C34),"","Check amount"))))
E35: =IF(AND(A35="",C35=""),"",IF(A35="","No order",IF(COUNTIF(Orders!$A$5:$A$64,A35)=0,"No order",IF(ISNUMBER(C35),"","Check amount"))))
E36: =IF(AND(A36="",C36=""),"",IF(A36="","No order",IF(COUNTIF(Orders!$A$5:$A$64,A36)=0,"No order",IF(ISNUMBER(C36),"","Check amount"))))
... E104: =IF(AND(A104="",C104=""),"",IF(A104="","No order",IF(COUNTIF(Orders!$A$5:$A$64,A104)=0,"No order",IF(ISNUMBER(C104),"","Check amount"))))

Sheet Settings
A1: As-of date | B1: 46326
A2: Settings check | B2: =IF(ISNUMBER(B1),"OK","Type a real date in the yellow cell")
A4: The as-of date is typed on purpose, so the Past due labels do not change when the file is opened later.

Sheet How to use
A1: Tidy Tabs: Track Deposits and Balance Due on Custom Orders
A3: 1. Settings tab: type the as-of date in B1 (yellow, 10/31/2026). B2 shows OK when B1 is a real date.
A4: 2. Orders tab: one row per order in A5:E64 (yellow): order number, customer, item, order total, due date. The sample has 12 fictional orders.
A5: 3. Payments tab: one row per payment in A5:D104 (yellow): order number, date, amount, method. The sample has 20 fictional payments. Column E says No order when the order number is not on the Orders tab, or Check amount when the amount is text.
A6: 4. Paid so far, Orders F5: =IF(A5="","",SUMIF(Payments!$A$5:$A$104,A5,Payments!$C$5:$C$104)). SUMIF ignores capital letters but not extra spaces, and it skips amounts stored as text.
A7: 5. Balance due, G5: =ROUND(D5-F5,2). Negative means the customer paid more than the order total.
A8: 6. Status, H5: Overpaid, Paid in full, Past due (balance above $0.00 and the due date is before the as-of date), Deposit received or Awaiting deposit. A due date equal to the as-of date is not Past due.
A9: 7. Deposit percent, I5: =ROUND(F5/D5,4) shown as a percent.
A10: 8. Summary, K2:L11. L11 is the CHECK: it shows OK when ordered minus received equals the balance due, every payment has an order and a numeric amount, no order number is listed twice and the settings are valid.
A11: 9. To make Past due move each day, type =TODAY() in Settings B1. The statuses then change when you open the file later.
A12: 10. This sheet only does arithmetic. It does not say whether a deposit is refundable or what a contract requires.
A14: Customers, orders and amounts are fictional. Checked in LibreOffice Calc only; not opened in Excel or Google Sheets.
A15: Google Sheets: File > Import > Upload this .xlsx.
