Workbook

Sheet Purchases
A1: Purchase date | B1: Item | C1: Quantity | D1: Unit cost | E1: Line total
A2: 46209 | B2: Soy wax (lb) | C2: 10 | D2: 4 | E2: =C2*D2
A3: 46223 | B3: Cotton wicks | C3: 200 | D3: 0.12 | E3: =C3*D3
A4: 46237 | B4: Soy wax (lb) | C4: 40 | D4: 3.5 | E4: =C4*D4
A5: 46246 | B5: Glass jars | C5: 48 | D5: 1.85 | E5: =C5*D5
A6: 46259 | B6: Cotton wicks | C6: 500 | D6: 0.09 | E6: =C6*D6
A7: 46272 | B7: Soy wax (lb) | C7: 25 | D7: 3.8 | E7: =C7*D7
A8: 46280 | B8: Glass jars | C8: 96 | D8: 1.6 | E8: =C8*D8
A9: 46287 | B9: Cotton wicks | C9: 300 | D9: 0.1 | E9: =C9*D9
A10: 46294 | B10: Glass jars | C10: 24 | D10: 2.1 | E10: =C10*D10

Sheet Summary
A1: Item | B1: Total quantity | C1: Total spent | D1: Weighted avg (SUMIFS) | E1: Weighted avg (SUMPRODUCT) | F1: Simple average | G1: Difference
A2: Soy wax (lb) | B2: =SUMIFS(Purchases!$C$2:$C$40,Purchases!$B$2:$B$40,A2) | C2: =SUMIFS(Purchases!$E$2:$E$40,Purchases!$B$2:$B$40,A2) | D2: =C2/B2 | E2: =SUMPRODUCT((Purchases!$B$2:$B$40=A2)*Purchases!$C$2:$C$40*Purchases!$D$2:$D$40)/B2 | F2: =AVERAGEIFS(Purchases!$D$2:$D$40,Purchases!$B$2:$B$40,A2) | G2: =ROUND(D2-F2,4)
A3: Cotton wicks | B3: =SUMIFS(Purchases!$C$2:$C$40,Purchases!$B$2:$B$40,A3) | C3: =SUMIFS(Purchases!$E$2:$E$40,Purchases!$B$2:$B$40,A3) | D3: =C3/B3 | E3: =SUMPRODUCT((Purchases!$B$2:$B$40=A3)*Purchases!$C$2:$C$40*Purchases!$D$2:$D$40)/B3 | F3: =AVERAGEIFS(Purchases!$D$2:$D$40,Purchases!$B$2:$B$40,A3) | G3: =ROUND(D3-F3,4)
A4: Glass jars | B4: =SUMIFS(Purchases!$C$2:$C$40,Purchases!$B$2:$B$40,A4) | C4: =SUMIFS(Purchases!$E$2:$E$40,Purchases!$B$2:$B$40,A4) | D4: =C4/B4 | E4: =SUMPRODUCT((Purchases!$B$2:$B$40=A4)*Purchases!$C$2:$C$40*Purchases!$D$2:$D$40)/B4 | F4: =AVERAGEIFS(Purchases!$D$2:$D$40,Purchases!$B$2:$B$40,A4) | G4: =ROUND(D4-F4,4)

Sheet How to use
A1: Tidy Tabs: Weighted Average Cost With SUMPRODUCT
A3: 1. Purchases tab: one row per purchase with the date, item, quantity, and unit cost you paid. Column E is quantity times unit cost.
A4: 2. Summary tab, column E: =SUMPRODUCT((Purchases!$B$2:$B$40=A2)*Purchases!$C$2:$C$40*Purchases!$D$2:$D$40)/B2. It multiplies quantity by unit cost for the rows that match the item, adds them up, and divides by the total quantity.
A5: 3. Column D gives the same answer with SUMIFS: total spent divided by total quantity (=C2/B2).
A6: 4. Column F, =AVERAGEIFS(...), is the simple average of the unit costs. It ignores how many units each purchase covered, so it is off whenever the quantities differ.
A7: 5. Example: 10 lb at $4.00 and 40 lb at $3.50 cost $180.00 for 50 lb, so the weighted average is $3.60 per lb. The simple average of $4.00 and $3.50 is $3.75.
A8: 6. The formulas read rows 2 to 40, so you can add purchases without editing them. Type each item name exactly the same way every time.
A9: 7. This is an average unit cost of what you bought. It is not an inventory valuation method or tax advice.
A11: Items, quantities, and prices are fictional. Checked in LibreOffice Calc only; not opened in Excel or Google Sheets.
A12: Google Sheets: File > Import > Upload this .xlsx.
