Workbook

Sheet Shops
A1: Fictional shops and rates. Commission rate = the share of each sale the shop keeps. Paid so far = what the shop has already sent you.
A4: Shop name | B4: Commission rate (shop keeps) | C4: Paid to you so far | D4: Gross sales | E4: Shop's cut | F4: Your share | G4: Still owed to you | H4: Items sold | I4: Flag
A5: Maple Street Gifts | B5: 0.3 | C5: 150 | D5: =IF(A5="","",SUMIFS(Sales!$F$5:$F$204,Sales!$B$5:$B$204,A5)) | E5: =IF(A5="","",SUMIFS(Sales!$G$5:$G$204,Sales!$B$5:$B$204,A5)) | F5: =IF(A5="","",SUMIFS(Sales!$H$5:$H$204,Sales!$B$5:$B$204,A5)) | G5: =IF(A5="","",IF(AND(C5<>"",NOT(ISNUMBER(C5))),"Check paid",ROUND(F5-N(C5),2))) | H5: =IF(A5="","",SUMIFS(Sales!$E$5:$E$204,Sales!$B$5:$B$204,A5)) | I5: =IF(A5="","",IF(NOT(AND(ISNUMBER(B5),B5>=0,B5<=1)),"Check rate",IF(NOT(ISNUMBER(G5)),"Check paid",IF(G5<0,"Check: paid more than owed","")))) | K5: Shops listed | L5: =COUNTA($A$5:$A$14)
A6: Harbor Art Co-op | B6: 0.4 | C6: 0 | D6: =IF(A6="","",SUMIFS(Sales!$F$5:$F$204,Sales!$B$5:$B$204,A6)) | E6: =IF(A6="","",SUMIFS(Sales!$G$5:$G$204,Sales!$B$5:$B$204,A6)) | F6: =IF(A6="","",SUMIFS(Sales!$H$5:$H$204,Sales!$B$5:$B$204,A6)) | G6: =IF(A6="","",IF(AND(C6<>"",NOT(ISNUMBER(C6))),"Check paid",ROUND(F6-N(C6),2))) | H6: =IF(A6="","",SUMIFS(Sales!$E$5:$E$204,Sales!$B$5:$B$204,A6)) | I6: =IF(A6="","",IF(NOT(AND(ISNUMBER(B6),B6>=0,B6<=1)),"Check rate",IF(NOT(ISNUMBER(G6)),"Check paid",IF(G6<0,"Check: paid more than owed","")))) | K6: Sale rows | L6: =COUNTIF(Sales!$F$5:$F$204,">0")+COUNTIF(Sales!$F$5:$F$204,"<=0")
A7: Cedar & Stone Boutique | B7: 0.35 | C7: 85 | D7: =IF(A7="","",SUMIFS(Sales!$F$5:$F$204,Sales!$B$5:$B$204,A7)) | E7: =IF(A7="","",SUMIFS(Sales!$G$5:$G$204,Sales!$B$5:$B$204,A7)) | F7: =IF(A7="","",SUMIFS(Sales!$H$5:$H$204,Sales!$B$5:$B$204,A7)) | G7: =IF(A7="","",IF(AND(C7<>"",NOT(ISNUMBER(C7))),"Check paid",ROUND(F7-N(C7),2))) | H7: =IF(A7="","",SUMIFS(Sales!$E$5:$E$204,Sales!$B$5:$B$204,A7)) | I7: =IF(A7="","",IF(NOT(AND(ISNUMBER(B7),B7>=0,B7<=1)),"Check rate",IF(NOT(ISNUMBER(G7)),"Check paid",IF(G7<0,"Check: paid more than owed","")))) | K7: Sales rows with an unlisted shop or bad rate | L7: =COUNTIF(Sales!$G$5:$G$204,"Check shop")
D8: =IF(A8="","",SUMIFS(Sales!$F$5:$F$204,Sales!$B$5:$B$204,A8)) | E8: =IF(A8="","",SUMIFS(Sales!$G$5:$G$204,Sales!$B$5:$B$204,A8)) | F8: =IF(A8="","",SUMIFS(Sales!$H$5:$H$204,Sales!$B$5:$B$204,A8)) | G8: =IF(A8="","",IF(AND(C8<>"",NOT(ISNUMBER(C8))),"Check paid",ROUND(F8-N(C8),2))) | H8: =IF(A8="","",SUMIFS(Sales!$E$5:$E$204,Sales!$B$5:$B$204,A8)) | I8: =IF(A8="","",IF(NOT(AND(ISNUMBER(B8),B8>=0,B8<=1)),"Check rate",IF(NOT(ISNUMBER(G8)),"Check paid",IF(G8<0,"Check: paid more than owed","")))) | K8: Sales rows with a missing price or quantity | L8: =COUNTIF(Sales!$F$5:$F$204,"Check amounts")
D9: =IF(A9="","",SUMIFS(Sales!$F$5:$F$204,Sales!$B$5:$B$204,A9)) | E9: =IF(A9="","",SUMIFS(Sales!$G$5:$G$204,Sales!$B$5:$B$204,A9)) | F9: =IF(A9="","",SUMIFS(Sales!$H$5:$H$204,Sales!$B$5:$B$204,A9)) | G9: =IF(A9="","",IF(AND(C9<>"",NOT(ISNUMBER(C9))),"Check paid",ROUND(F9-N(C9),2))) | H9: =IF(A9="","",SUMIFS(Sales!$E$5:$E$204,Sales!$B$5:$B$204,A9)) | I9: =IF(A9="","",IF(NOT(AND(ISNUMBER(B9),B9>=0,B9<=1)),"Check rate",IF(NOT(ISNUMBER(G9)),"Check paid",IF(G9<0,"Check: paid more than owed","")))) | K9: Shops paid more than they owe | L9: =COUNTIF($I$5:$I$14,"Check: paid*")
D10: =IF(A10="","",SUMIFS(Sales!$F$5:$F$204,Sales!$B$5:$B$204,A10)) | E10: =IF(A10="","",SUMIFS(Sales!$G$5:$G$204,Sales!$B$5:$B$204,A10)) | F10: =IF(A10="","",SUMIFS(Sales!$H$5:$H$204,Sales!$B$5:$B$204,A10)) | G10: =IF(A10="","",IF(AND(C10<>"",NOT(ISNUMBER(C10))),"Check paid",ROUND(F10-N(C10),2))) | H10: =IF(A10="","",SUMIFS(Sales!$E$5:$E$204,Sales!$B$5:$B$204,A10)) | I10: =IF(A10="","",IF(NOT(AND(ISNUMBER(B10),B10>=0,B10<=1)),"Check rate",IF(NOT(ISNUMBER(G10)),"Check paid",IF(G10<0,"Check: paid more than owed","")))) | K10: Gross sales on the Sales tab | L10: =SUM(Sales!$F$5:$F$204)
D11: =IF(A11="","",SUMIFS(Sales!$F$5:$F$204,Sales!$B$5:$B$204,A11)) | E11: =IF(A11="","",SUMIFS(Sales!$G$5:$G$204,Sales!$B$5:$B$204,A11)) | F11: =IF(A11="","",SUMIFS(Sales!$H$5:$H$204,Sales!$B$5:$B$204,A11)) | G11: =IF(A11="","",IF(AND(C11<>"",NOT(ISNUMBER(C11))),"Check paid",ROUND(F11-N(C11),2))) | H11: =IF(A11="","",SUMIFS(Sales!$E$5:$E$204,Sales!$B$5:$B$204,A11)) | I11: =IF(A11="","",IF(NOT(AND(ISNUMBER(B11),B11>=0,B11<=1)),"Check rate",IF(NOT(ISNUMBER(G11)),"Check paid",IF(G11<0,"Check: paid more than owed","")))) | K11: Shop's cut on the Sales tab | L11: =SUM(Sales!$G$5:$G$204)
D12: =IF(A12="","",SUMIFS(Sales!$F$5:$F$204,Sales!$B$5:$B$204,A12)) | E12: =IF(A12="","",SUMIFS(Sales!$G$5:$G$204,Sales!$B$5:$B$204,A12)) | F12: =IF(A12="","",SUMIFS(Sales!$H$5:$H$204,Sales!$B$5:$B$204,A12)) | G12: =IF(A12="","",IF(AND(C12<>"",NOT(ISNUMBER(C12))),"Check paid",ROUND(F12-N(C12),2))) | H12: =IF(A12="","",SUMIFS(Sales!$E$5:$E$204,Sales!$B$5:$B$204,A12)) | I12: =IF(A12="","",IF(NOT(AND(ISNUMBER(B12),B12>=0,B12<=1)),"Check rate",IF(NOT(ISNUMBER(G12)),"Check paid",IF(G12<0,"Check: paid more than owed","")))) | K12: Your share on the Sales tab | L12: =SUM(Sales!$H$5:$H$204)
D13: =IF(A13="","",SUMIFS(Sales!$F$5:$F$204,Sales!$B$5:$B$204,A13)) | E13: =IF(A13="","",SUMIFS(Sales!$G$5:$G$204,Sales!$B$5:$B$204,A13)) | F13: =IF(A13="","",SUMIFS(Sales!$H$5:$H$204,Sales!$B$5:$B$204,A13)) | G13: =IF(A13="","",IF(AND(C13<>"",NOT(ISNUMBER(C13))),"Check paid",ROUND(F13-N(C13),2))) | H13: =IF(A13="","",SUMIFS(Sales!$E$5:$E$204,Sales!$B$5:$B$204,A13)) | I13: =IF(A13="","",IF(NOT(AND(ISNUMBER(B13),B13>=0,B13<=1)),"Check rate",IF(NOT(ISNUMBER(G13)),"Check paid",IF(G13<0,"Check: paid more than owed","")))) | K13: Check: gross = cut + your share, every sale has a listed shop and amounts, no shop is listed twice | L13: =IF(AND(ROUND(SUM(Sales!$F$5:$F$204)-SUM(Sales!$G$5:$G$204)-SUM(Sales!$H$5:$H$204),2)=0,COUNTIF(Sales!$G$5:$G$204,"Check shop")=0,COUNTIF(Sales!$F$5:$F$204,"Check amounts")=0,SUMPRODUCT(($A$5:$A$14<>"")*(COUNTIF($A$5:$A$14,$A$5:$A$14)>1))=0,COUNTIF($I$5:$I$14,"Check rate")+COUNTIF($I$5:$I$14,"Check paid")=0,ROUND(SUM($F$5:$F$14)-SUM(Sales!$H$5:$H$204),2)=0,COUNTA(Sales!A205:E500)=0),"OK","Check")
D14: =IF(A14="","",SUMIFS(Sales!$F$5:$F$204,Sales!$B$5:$B$204,A14)) | E14: =IF(A14="","",SUMIFS(Sales!$G$5:$G$204,Sales!$B$5:$B$204,A14)) | F14: =IF(A14="","",SUMIFS(Sales!$H$5:$H$204,Sales!$B$5:$B$204,A14)) | G14: =IF(A14="","",IF(AND(C14<>"",NOT(ISNUMBER(C14))),"Check paid",ROUND(F14-N(C14),2))) | H14: =IF(A14="","",SUMIFS(Sales!$E$5:$E$204,Sales!$B$5:$B$204,A14)) | I14: =IF(A14="","",IF(NOT(AND(ISNUMBER(B14),B14>=0,B14<=1)),"Check rate",IF(NOT(ISNUMBER(G14)),"Check paid",IF(G14<0,"Check: paid more than owed",""))))
A15: Total | C15: =SUM(C5:C14) | D15: =SUM(D5:D14) | E15: =SUM(E5:E14) | F15: =SUM(F5:F14) | G15: =SUM(G5:G14) | H15: =SUM(H5:H14)

Sheet Sales
A1: Fictional sample sales. One row per sale: yellow cells are yours to type. Gray cells are formulas.
A4: Sale date | B4: Shop | C4: Item | D4: Price each | E4: Qty | F4: Gross | G4: Shop's cut | H4: Your share
A5: 46266 | B5: Maple Street Gifts | C5: Soy candle, large | D5: 18 | E5: 2 | F5: =IF(COUNTA(A5:E5)=0,"",IF(AND(ISNUMBER(D5),ISNUMBER(E5)),ROUND(D5*E5,2),"Check amounts")) | G5: =IF(NOT(ISNUMBER(F5)),"",IF(COUNTIFS(Shops!$A$5:$A$14,B5,Shops!$B$5:$B$14,">=0",Shops!$B$5:$B$14,"<=1")=0,"Check shop",ROUND(F5*INDEX(Shops!$B$5:$B$14,MATCH(B5,Shops!$A$5:$A$14,0)),2))) | H5: =IF(ISNUMBER(G5),ROUND(F5-G5,2),"")
A6: 46267 | B6: Harbor Art Co-op | C6: Ceramic mug | D6: 24 | E6: 1 | F6: =IF(COUNTA(A6:E6)=0,"",IF(AND(ISNUMBER(D6),ISNUMBER(E6)),ROUND(D6*E6,2),"Check amounts")) | G6: =IF(NOT(ISNUMBER(F6)),"",IF(COUNTIFS(Shops!$A$5:$A$14,B6,Shops!$B$5:$B$14,">=0",Shops!$B$5:$B$14,"<=1")=0,"Check shop",ROUND(F6*INDEX(Shops!$B$5:$B$14,MATCH(B6,Shops!$A$5:$A$14,0)),2))) | H6: =IF(ISNUMBER(G6),ROUND(F6-G6,2),"")
A7: 46269 | B7: Cedar & Stone Boutique | C7: Greeting card 6-pack | D7: 12.5 | E7: 3 | F7: =IF(COUNTA(A7:E7)=0,"",IF(AND(ISNUMBER(D7),ISNUMBER(E7)),ROUND(D7*E7,2),"Check amounts")) | G7: =IF(NOT(ISNUMBER(F7)),"",IF(COUNTIFS(Shops!$A$5:$A$14,B7,Shops!$B$5:$B$14,">=0",Shops!$B$5:$B$14,"<=1")=0,"Check shop",ROUND(F7*INDEX(Shops!$B$5:$B$14,MATCH(B7,Shops!$A$5:$A$14,0)),2))) | H7: =IF(ISNUMBER(G7),ROUND(F7-G7,2),"")
A8: 46271 | B8: Maple Street Gifts | C8: Greeting card 6-pack | D8: 12 | E8: 1 | F8: =IF(COUNTA(A8:E8)=0,"",IF(AND(ISNUMBER(D8),ISNUMBER(E8)),ROUND(D8*E8,2),"Check amounts")) | G8: =IF(NOT(ISNUMBER(F8)),"",IF(COUNTIFS(Shops!$A$5:$A$14,B8,Shops!$B$5:$B$14,">=0",Shops!$B$5:$B$14,"<=1")=0,"Check shop",ROUND(F8*INDEX(Shops!$B$5:$B$14,MATCH(B8,Shops!$A$5:$A$14,0)),2))) | H8: =IF(ISNUMBER(G8),ROUND(F8-G8,2),"")
A9: 46273 | B9: Harbor Art Co-op | C9: Watercolor print | D9: 35 | E9: 2 | F9: =IF(COUNTA(A9:E9)=0,"",IF(AND(ISNUMBER(D9),ISNUMBER(E9)),ROUND(D9*E9,2),"Check amounts")) | G9: =IF(NOT(ISNUMBER(F9)),"",IF(COUNTIFS(Shops!$A$5:$A$14,B9,Shops!$B$5:$B$14,">=0",Shops!$B$5:$B$14,"<=1")=0,"Check shop",ROUND(F9*INDEX(Shops!$B$5:$B$14,MATCH(B9,Shops!$A$5:$A$14,0)),2))) | H9: =IF(ISNUMBER(G9),ROUND(F9-G9,2),"")
A10: 46275 | B10: Cedar & Stone Boutique | C10: Greeting card 6-pack | D10: 12.5 | E10: 3 | F10: =IF(COUNTA(A10:E10)=0,"",IF(AND(ISNUMBER(D10),ISNUMBER(E10)),ROUND(D10*E10,2),"Check amounts")) | G10: =IF(NOT(ISNUMBER(F10)),"",IF(COUNTIFS(Shops!$A$5:$A$14,B10,Shops!$B$5:$B$14,">=0",Shops!$B$5:$B$14,"<=1")=0,"Check shop",ROUND(F10*INDEX(Shops!$B$5:$B$14,MATCH(B10,Shops!$A$5:$A$14,0)),2))) | H10: =IF(ISNUMBER(G10),ROUND(F10-G10,2),"")
A11: 46277 | B11: Maple Street Gifts | C11: Ceramic mug | D11: 22 | E11: 4 | F11: =IF(COUNTA(A11:E11)=0,"",IF(AND(ISNUMBER(D11),ISNUMBER(E11)),ROUND(D11*E11,2),"Check amounts")) | G11: =IF(NOT(ISNUMBER(F11)),"",IF(COUNTIFS(Shops!$A$5:$A$14,B11,Shops!$B$5:$B$14,">=0",Shops!$B$5:$B$14,"<=1")=0,"Check shop",ROUND(F11*INDEX(Shops!$B$5:$B$14,MATCH(B11,Shops!$A$5:$A$14,0)),2))) | H11: =IF(ISNUMBER(G11),ROUND(F11-G11,2),"")
A12: 46279 | B12: Harbor Art Co-op | C12: Soy candle, large | D12: 20 | E12: 1 | F12: =IF(COUNTA(A12:E12)=0,"",IF(AND(ISNUMBER(D12),ISNUMBER(E12)),ROUND(D12*E12,2),"Check amounts")) | G12: =IF(NOT(ISNUMBER(F12)),"",IF(COUNTIFS(Shops!$A$5:$A$14,B12,Shops!$B$5:$B$14,">=0",Shops!$B$5:$B$14,"<=1")=0,"Check shop",ROUND(F12*INDEX(Shops!$B$5:$B$14,MATCH(B12,Shops!$A$5:$A$14,0)),2))) | H12: =IF(ISNUMBER(G12),ROUND(F12-G12,2),"")
A13: 46281 | B13: Cedar & Stone Boutique | C13: Ceramic mug | D13: 23 | E13: 1 | F13: =IF(COUNTA(A13:E13)=0,"",IF(AND(ISNUMBER(D13),ISNUMBER(E13)),ROUND(D13*E13,2),"Check amounts")) | G13: =IF(NOT(ISNUMBER(F13)),"",IF(COUNTIFS(Shops!$A$5:$A$14,B13,Shops!$B$5:$B$14,">=0",Shops!$B$5:$B$14,"<=1")=0,"Check shop",ROUND(F13*INDEX(Shops!$B$5:$B$14,MATCH(B13,Shops!$A$5:$A$14,0)),2))) | H13: =IF(ISNUMBER(G13),ROUND(F13-G13,2),"")
A14: 46283 | B14: Maple Street Gifts | C14: Soy candle, large | D14: 18 | E14: 2 | F14: =IF(COUNTA(A14:E14)=0,"",IF(AND(ISNUMBER(D14),ISNUMBER(E14)),ROUND(D14*E14,2),"Check amounts")) | G14: =IF(NOT(ISNUMBER(F14)),"",IF(COUNTIFS(Shops!$A$5:$A$14,B14,Shops!$B$5:$B$14,">=0",Shops!$B$5:$B$14,"<=1")=0,"Check shop",ROUND(F14*INDEX(Shops!$B$5:$B$14,MATCH(B14,Shops!$A$5:$A$14,0)),2))) | H14: =IF(ISNUMBER(G14),ROUND(F14-G14,2),"")
A15: 46285 | B15: Harbor Art Co-op | C15: Ceramic mug | D15: 24 | E15: 1 | F15: =IF(COUNTA(A15:E15)=0,"",IF(AND(ISNUMBER(D15),ISNUMBER(E15)),ROUND(D15*E15,2),"Check amounts")) | G15: =IF(NOT(ISNUMBER(F15)),"",IF(COUNTIFS(Shops!$A$5:$A$14,B15,Shops!$B$5:$B$14,">=0",Shops!$B$5:$B$14,"<=1")=0,"Check shop",ROUND(F15*INDEX(Shops!$B$5:$B$14,MATCH(B15,Shops!$A$5:$A$14,0)),2))) | H15: =IF(ISNUMBER(G15),ROUND(F15-G15,2),"")
A16: 46287 | B16: Cedar & Stone Boutique | C16: Greeting card 6-pack | D16: 12.5 | E16: 2 | F16: =IF(COUNTA(A16:E16)=0,"",IF(AND(ISNUMBER(D16),ISNUMBER(E16)),ROUND(D16*E16,2),"Check amounts")) | G16: =IF(NOT(ISNUMBER(F16)),"",IF(COUNTIFS(Shops!$A$5:$A$14,B16,Shops!$B$5:$B$14,">=0",Shops!$B$5:$B$14,"<=1")=0,"Check shop",ROUND(F16*INDEX(Shops!$B$5:$B$14,MATCH(B16,Shops!$A$5:$A$14,0)),2))) | H16: =IF(ISNUMBER(G16),ROUND(F16-G16,2),"")
... A34: 46323 | B34: Cedar & Stone Boutique | C34: Greeting card 6-pack | D34: 12.5 | E34: 4 | F34: =IF(COUNTA(A34:E34)=0,"",IF(AND(ISNUMBER(D34),ISNUMBER(E34)),ROUND(D34*E34,2),"Check amounts")) | G34: =IF(NOT(ISNUMBER(F34)),"",IF(COUNTIFS(Shops!$A$5:$A$14,B34,Shops!$B$5:$B$14,">=0",Shops!$B$5:$B$14,"<=1")=0,"Check shop",ROUND(F34*INDEX(Shops!$B$5:$B$14,MATCH(B34,Shops!$A$5:$A$14,0)),2))) | H34: =IF(ISNUMBER(G34),ROUND(F34-G34,2),"")
F35: =IF(COUNTA(A35:E35)=0,"",IF(AND(ISNUMBER(D35),ISNUMBER(E35)),ROUND(D35*E35,2),"Check amounts")) | G35: =IF(NOT(ISNUMBER(F35)),"",IF(COUNTIFS(Shops!$A$5:$A$14,B35,Shops!$B$5:$B$14,">=0",Shops!$B$5:$B$14,"<=1")=0,"Check shop",ROUND(F35*INDEX(Shops!$B$5:$B$14,MATCH(B35,Shops!$A$5:$A$14,0)),2))) | H35: =IF(ISNUMBER(G35),ROUND(F35-G35,2),"")
F36: =IF(COUNTA(A36:E36)=0,"",IF(AND(ISNUMBER(D36),ISNUMBER(E36)),ROUND(D36*E36,2),"Check amounts")) | G36: =IF(NOT(ISNUMBER(F36)),"",IF(COUNTIFS(Shops!$A$5:$A$14,B36,Shops!$B$5:$B$14,">=0",Shops!$B$5:$B$14,"<=1")=0,"Check shop",ROUND(F36*INDEX(Shops!$B$5:$B$14,MATCH(B36,Shops!$A$5:$A$14,0)),2))) | H36: =IF(ISNUMBER(G36),ROUND(F36-G36,2),"")
F37: =IF(COUNTA(A37:E37)=0,"",IF(AND(ISNUMBER(D37),ISNUMBER(E37)),ROUND(D37*E37,2),"Check amounts")) | G37: =IF(NOT(ISNUMBER(F37)),"",IF(COUNTIFS(Shops!$A$5:$A$14,B37,Shops!$B$5:$B$14,">=0",Shops!$B$5:$B$14,"<=1")=0,"Check shop",ROUND(F37*INDEX(Shops!$B$5:$B$14,MATCH(B37,Shops!$A$5:$A$14,0)),2))) | H37: =IF(ISNUMBER(G37),ROUND(F37-G37,2),"")
F38: =IF(COUNTA(A38:E38)=0,"",IF(AND(ISNUMBER(D38),ISNUMBER(E38)),ROUND(D38*E38,2),"Check amounts")) | G38: =IF(NOT(ISNUMBER(F38)),"",IF(COUNTIFS(Shops!$A$5:$A$14,B38,Shops!$B$5:$B$14,">=0",Shops!$B$5:$B$14,"<=1")=0,"Check shop",ROUND(F38*INDEX(Shops!$B$5:$B$14,MATCH(B38,Shops!$A$5:$A$14,0)),2))) | H38: =IF(ISNUMBER(G38),ROUND(F38-G38,2),"")
F39: =IF(COUNTA(A39:E39)=0,"",IF(AND(ISNUMBER(D39),ISNUMBER(E39)),ROUND(D39*E39,2),"Check amounts")) | G39: =IF(NOT(ISNUMBER(F39)),"",IF(COUNTIFS(Shops!$A$5:$A$14,B39,Shops!$B$5:$B$14,">=0",Shops!$B$5:$B$14,"<=1")=0,"Check shop",ROUND(F39*INDEX(Shops!$B$5:$B$14,MATCH(B39,Shops!$A$5:$A$14,0)),2))) | H39: =IF(ISNUMBER(G39),ROUND(F39-G39,2),"")
F40: =IF(COUNTA(A40:E40)=0,"",IF(AND(ISNUMBER(D40),ISNUMBER(E40)),ROUND(D40*E40,2),"Check amounts")) | G40: =IF(NOT(ISNUMBER(F40)),"",IF(COUNTIFS(Shops!$A$5:$A$14,B40,Shops!$B$5:$B$14,">=0",Shops!$B$5:$B$14,"<=1")=0,"Check shop",ROUND(F40*INDEX(Shops!$B$5:$B$14,MATCH(B40,Shops!$A$5:$A$14,0)),2))) | H40: =IF(ISNUMBER(G40),ROUND(F40-G40,2),"")
F41: =IF(COUNTA(A41:E41)=0,"",IF(AND(ISNUMBER(D41),ISNUMBER(E41)),ROUND(D41*E41,2),"Check amounts")) | G41: =IF(NOT(ISNUMBER(F41)),"",IF(COUNTIFS(Shops!$A$5:$A$14,B41,Shops!$B$5:$B$14,">=0",Shops!$B$5:$B$14,"<=1")=0,"Check shop",ROUND(F41*INDEX(Shops!$B$5:$B$14,MATCH(B41,Shops!$A$5:$A$14,0)),2))) | H41: =IF(ISNUMBER(G41),ROUND(F41-G41,2),"")
F42: =IF(COUNTA(A42:E42)=0,"",IF(AND(ISNUMBER(D42),ISNUMBER(E42)),ROUND(D42*E42,2),"Check amounts")) | G42: =IF(NOT(ISNUMBER(F42)),"",IF(COUNTIFS(Shops!$A$5:$A$14,B42,Shops!$B$5:$B$14,">=0",Shops!$B$5:$B$14,"<=1")=0,"Check shop",ROUND(F42*INDEX(Shops!$B$5:$B$14,MATCH(B42,Shops!$A$5:$A$14,0)),2))) | H42: =IF(ISNUMBER(G42),ROUND(F42-G42,2),"")
F43: =IF(COUNTA(A43:E43)=0,"",IF(AND(ISNUMBER(D43),ISNUMBER(E43)),ROUND(D43*E43,2),"Check amounts")) | G43: =IF(NOT(ISNUMBER(F43)),"",IF(COUNTIFS(Shops!$A$5:$A$14,B43,Shops!$B$5:$B$14,">=0",Shops!$B$5:$B$14,"<=1")=0,"Check shop",ROUND(F43*INDEX(Shops!$B$5:$B$14,MATCH(B43,Shops!$A$5:$A$14,0)),2))) | H43: =IF(ISNUMBER(G43),ROUND(F43-G43,2),"")
F44: =IF(COUNTA(A44:E44)=0,"",IF(AND(ISNUMBER(D44),ISNUMBER(E44)),ROUND(D44*E44,2),"Check amounts")) | G44: =IF(NOT(ISNUMBER(F44)),"",IF(COUNTIFS(Shops!$A$5:$A$14,B44,Shops!$B$5:$B$14,">=0",Shops!$B$5:$B$14,"<=1")=0,"Check shop",ROUND(F44*INDEX(Shops!$B$5:$B$14,MATCH(B44,Shops!$A$5:$A$14,0)),2))) | H44: =IF(ISNUMBER(G44),ROUND(F44-G44,2),"")
F45: =IF(COUNTA(A45:E45)=0,"",IF(AND(ISNUMBER(D45),ISNUMBER(E45)),ROUND(D45*E45,2),"Check amounts")) | G45: =IF(NOT(ISNUMBER(F45)),"",IF(COUNTIFS(Shops!$A$5:$A$14,B45,Shops!$B$5:$B$14,">=0",Shops!$B$5:$B$14,"<=1")=0,"Check shop",ROUND(F45*INDEX(Shops!$B$5:$B$14,MATCH(B45,Shops!$A$5:$A$14,0)),2))) | H45: =IF(ISNUMBER(G45),ROUND(F45-G45,2),"")
F46: =IF(COUNTA(A46:E46)=0,"",IF(AND(ISNUMBER(D46),ISNUMBER(E46)),ROUND(D46*E46,2),"Check amounts")) | G46: =IF(NOT(ISNUMBER(F46)),"",IF(COUNTIFS(Shops!$A$5:$A$14,B46,Shops!$B$5:$B$14,">=0",Shops!$B$5:$B$14,"<=1")=0,"Check shop",ROUND(F46*INDEX(Shops!$B$5:$B$14,MATCH(B46,Shops!$A$5:$A$14,0)),2))) | H46: =IF(ISNUMBER(G46),ROUND(F46-G46,2),"")
... F204: =IF(COUNTA(A204:E204)=0,"",IF(AND(ISNUMBER(D204),ISNUMBER(E204)),ROUND(D204*E204,2),"Check amounts")) | G204: =IF(NOT(ISNUMBER(F204)),"",IF(COUNTIFS(Shops!$A$5:$A$14,B204,Shops!$B$5:$B$14,">=0",Shops!$B$5:$B$14,"<=1")=0,"Check shop",ROUND(F204*INDEX(Shops!$B$5:$B$14,MATCH(B204,Shops!$A$5:$A$14,0)),2))) | H204: =IF(ISNUMBER(G204),ROUND(F204-G204,2),"")

Sheet How to use
A1: Tidy Tabs: Calculate Consignment Payouts for Each Shop
A3: 1. Shops tab: list each shop once in A5:A14 (yellow), its commission rate in B (the share of each sale the shop keeps, formatted as a percent) and what it has already paid you in C. The sample has 3 fictional shops.
A4: 2. Sales tab: one row per sale in A5:E204 (yellow): date, shop, item, price each, quantity. The shop name must match the Shops list exactly (capital letters do not matter; a trailing space does). The sample has 30 fictional sales.
A5: 3. Gross, F5: =IF(COUNTA(A5:E5)=0,"",IF(AND(ISNUMBER(D5),ISNUMBER(E5)),ROUND(D5*E5,2),"Check amounts")).
A6: 4. Shop's cut, G5: the sale times the shop's rate, rounded to cents on each sale: =ROUND(F5*INDEX(Shops!$B$5:$B$14,MATCH(B5,Shops!$A$5:$A$14,0)),2). A shop that is not in the list, or has no rate between 0% and 100%, shows Check shop.
A7: 5. Your share, H5: =ROUND(F5-G5,2). Because the cut is rounded on each sale, the cut plus your share equals the gross to the cent.
A8: 6. Shops tab totals: D5 =SUMIFS(Sales!$F$5:$F$204,Sales!$B$5:$B$204,A5), E5 and F5 the same on columns G and H of Sales, H5 the quantity. Still owed to you, G5: =ROUND(F5-N(C5),2). A negative number means the shop has paid you more than your share; the Flag column says so.
A9: 7. L13 shows OK when gross = cut + your share, every sale has a listed shop and amounts, no shop is listed twice, rates and paid amounts are numbers, and nothing is typed below row 204 on the Sales tab. A shop paid more than it owes does not change L13; it is counted in L9.
A10: 8. This is arithmetic on the numbers you type. It does not say what your agreement with a shop requires, who owns unsold stock, or whether a shop collected sales tax.
A12: Shops, items, dates and amounts are fictional. Checked in LibreOffice Calc only; not opened in Excel or Google Sheets.
A13: Google Sheets: File > Import > Upload this .xlsx.
