Workbook

Sheet Time log
A1: Fictional freelance bookkeeper. Block size and rate are on the Settings tab. Yellow cells are yours to change.
A2: Start and End are clock times on the same day. A row with End before Start shows Check times.
A4: Date | B4: Client | C4: Task | D4: Start | E4: End | F4: Minutes worked | G4: Billed minutes | H4: Billed hours | I4: Amount | J4: Extra minutes billed
A5: 46300 | B5: Maple Dental | C5: Bank reconciliation | D5: 0.37638889 | E5: 0.40902778 | F5: =IF(AND(D5="",E5=""),"",IF(AND(ISNUMBER(D5),ISNUMBER(E5)),IF(E5>=D5,ROUND((E5-D5)*1440,0),"Check times"),"Check times")) | G5: =IF(ISNUMBER(F5),IF(Settings!$B$3<>"OK","Check settings",ROUNDUP(F5/Settings!$B$1,0)*Settings!$B$1),"") | H5: =IF(ISNUMBER(G5),G5/60,"") | I5: =IF(ISNUMBER(H5),ROUND(H5*Settings!$B$2,2),"") | J5: =IF(ISNUMBER(G5),G5-F5,"") | L5: Entries with a number of minutes | M5: =COUNT(F5:F64)
A6: 46300 | B6: Harbor Yoga | C6: Invoices | D6: 0.41666667 | E6: 0.44791667 | F6: =IF(AND(D6="",E6=""),"",IF(AND(ISNUMBER(D6),ISNUMBER(E6)),IF(E6>=D6,ROUND((E6-D6)*1440,0),"Check times"),"Check times")) | G6: =IF(ISNUMBER(F6),IF(Settings!$B$3<>"OK","Check settings",ROUNDUP(F6/Settings!$B$1,0)*Settings!$B$1),"") | H6: =IF(ISNUMBER(G6),G6/60,"") | I6: =IF(ISNUMBER(H6),ROUND(H6*Settings!$B$2,2),"") | J6: =IF(ISNUMBER(G6),G6-F6,"") | L6: Total actual minutes | M6: =SUM(F5:F64)
A7: 46300 | B7: Pine Street Bakery | C7: Payroll prep | D7: 0.41666667 | E7: 0.44861111 | F7: =IF(AND(D7="",E7=""),"",IF(AND(ISNUMBER(D7),ISNUMBER(E7)),IF(E7>=D7,ROUND((E7-D7)*1440,0),"Check times"),"Check times")) | G7: =IF(ISNUMBER(F7),IF(Settings!$B$3<>"OK","Check settings",ROUNDUP(F7/Settings!$B$1,0)*Settings!$B$1),"") | H7: =IF(ISNUMBER(G7),G7/60,"") | I7: =IF(ISNUMBER(H7),ROUND(H7*Settings!$B$2,2),"") | J7: =IF(ISNUMBER(G7),G7-F7,"") | L7: Total billed minutes | M7: =SUM(G5:G64)
A8: 46301 | B8: Maple Dental | C8: Phone call | D8: 0.55208333 | E8: 0.55208333 | F8: =IF(AND(D8="",E8=""),"",IF(AND(ISNUMBER(D8),ISNUMBER(E8)),IF(E8>=D8,ROUND((E8-D8)*1440,0),"Check times"),"Check times")) | G8: =IF(ISNUMBER(F8),IF(Settings!$B$3<>"OK","Check settings",ROUNDUP(F8/Settings!$B$1,0)*Settings!$B$1),"") | H8: =IF(ISNUMBER(G8),G8/60,"") | I8: =IF(ISNUMBER(H8),ROUND(H8*Settings!$B$2,2),"") | J8: =IF(ISNUMBER(G8),G8-F8,"") | L8: Extra minutes billed because of rounding | M8: =M7-M6
A9: 46301 | B9: Harbor Yoga | C9: Month-end close | D9: 0.35416667 | E9: 0.39652778 | F9: =IF(AND(D9="",E9=""),"",IF(AND(ISNUMBER(D9),ISNUMBER(E9)),IF(E9>=D9,ROUND((E9-D9)*1440,0),"Check times"),"Check times")) | G9: =IF(ISNUMBER(F9),IF(Settings!$B$3<>"OK","Check settings",ROUNDUP(F9/Settings!$B$1,0)*Settings!$B$1),"") | H9: =IF(ISNUMBER(G9),G9/60,"") | I9: =IF(ISNUMBER(H9),ROUND(H9*Settings!$B$2,2),"") | J9: =IF(ISNUMBER(G9),G9-F9,"") | L9: Total amount | M9: =SUM(I5:I64)
A10: 46301 | B10: Cedar Cycles | C10: Quick question | D10: 0.58333333 | E10: 0.58402778 | F10: =IF(AND(D10="",E10=""),"",IF(AND(ISNUMBER(D10),ISNUMBER(E10)),IF(E10>=D10,ROUND((E10-D10)*1440,0),"Check times"),"Check times")) | G10: =IF(ISNUMBER(F10),IF(Settings!$B$3<>"OK","Check settings",ROUNDUP(F10/Settings!$B$1,0)*Settings!$B$1),"") | H10: =IF(ISNUMBER(G10),G10/60,"") | I10: =IF(ISNUMBER(H10),ROUND(H10*Settings!$B$2,2),"") | J10: =IF(ISNUMBER(G10),G10-F10,"") | L10: Rows that show Check times | M10: =COUNTIF(F5:F64,"Check*")
A11: 46302 | B11: Pine Street Bakery | C11: Sales tax report | D11: 0.46527778 | E11: 0.52777778 | F11: =IF(AND(D11="",E11=""),"",IF(AND(ISNUMBER(D11),ISNUMBER(E11)),IF(E11>=D11,ROUND((E11-D11)*1440,0),"Check times"),"Check times")) | G11: =IF(ISNUMBER(F11),IF(Settings!$B$3<>"OK","Check settings",ROUNDUP(F11/Settings!$B$1,0)*Settings!$B$1),"") | H11: =IF(ISNUMBER(G11),G11/60,"") | I11: =IF(ISNUMBER(H11),ROUND(H11*Settings!$B$2,2),"") | J11: =IF(ISNUMBER(G11),G11-F11,"") | L11: Check: settings valid, every billed total is a whole number of blocks, extra is under one block | M11: =IF(AND(Settings!B3="OK",COUNT(G5:G64)=COUNT(F5:F64),SUMPRODUCT(--ISNUMBER(G5:G64),--(IFERROR(MOD(G5:G64,Settings!B1),0)<>0))=0,COUNTIF(J5:J64,"<0")=0,COUNTIF(J5:J64,">="&Settings!B1)=0,ROUND(M8-SUM(J5:J64),6)=0,COUNTA(A65:E500)=0),"OK","CHECK")
A12: 46302 | B12: Cedar Cycles | C12: Receipts sort | D12: 0.62847222 | E12: 0.63888889 | F12: =IF(AND(D12="",E12=""),"",IF(AND(ISNUMBER(D12),ISNUMBER(E12)),IF(E12>=D12,ROUND((E12-D12)*1440,0),"Check times"),"Check times")) | G12: =IF(ISNUMBER(F12),IF(Settings!$B$3<>"OK","Check settings",ROUNDUP(F12/Settings!$B$1,0)*Settings!$B$1),"") | H12: =IF(ISNUMBER(G12),G12/60,"") | I12: =IF(ISNUMBER(H12),ROUND(H12*Settings!$B$2,2),"") | J12: =IF(ISNUMBER(G12),G12-F12,"")
A13: 46303 | B13: Maple Dental | C13: Vendor bills | D13: 0.375 | E13: 0.42638889 | F13: =IF(AND(D13="",E13=""),"",IF(AND(ISNUMBER(D13),ISNUMBER(E13)),IF(E13>=D13,ROUND((E13-D13)*1440,0),"Check times"),"Check times")) | G13: =IF(ISNUMBER(F13),IF(Settings!$B$3<>"OK","Check settings",ROUNDUP(F13/Settings!$B$1,0)*Settings!$B$1),"") | H13: =IF(ISNUMBER(G13),G13/60,"") | I13: =IF(ISNUMBER(H13),ROUND(H13*Settings!$B$2,2),"") | J13: =IF(ISNUMBER(G13),G13-F13,"")
A14: 46303 | B14: Harbor Yoga | C14: Budget review | D14: 0.6875 | E14: 0.70972222 | F14: =IF(AND(D14="",E14=""),"",IF(AND(ISNUMBER(D14),ISNUMBER(E14)),IF(E14>=D14,ROUND((E14-D14)*1440,0),"Check times"),"Check times")) | G14: =IF(ISNUMBER(F14),IF(Settings!$B$3<>"OK","Check settings",ROUNDUP(F14/Settings!$B$1,0)*Settings!$B$1),"") | H14: =IF(ISNUMBER(G14),G14/60,"") | I14: =IF(ISNUMBER(H14),ROUND(H14*Settings!$B$2,2),"") | J14: =IF(ISNUMBER(G14),G14-F14,"")
A15: 46304 | B15: Pine Street Bakery | C15: Cleanup of old entries | D15: 0.33333333 | E15: 0.45833333 | F15: =IF(AND(D15="",E15=""),"",IF(AND(ISNUMBER(D15),ISNUMBER(E15)),IF(E15>=D15,ROUND((E15-D15)*1440,0),"Check times"),"Check times")) | G15: =IF(ISNUMBER(F15),IF(Settings!$B$3<>"OK","Check settings",ROUNDUP(F15/Settings!$B$1,0)*Settings!$B$1),"") | H15: =IF(ISNUMBER(G15),G15/60,"") | I15: =IF(ISNUMBER(H15),ROUND(H15*Settings!$B$2,2),"") | J15: =IF(ISNUMBER(G15),G15-F15,"")
A16: 46304 | B16: Cedar Cycles | C16: Email follow-up | D16: 0.54166667 | E16: 0.54652778 | F16: =IF(AND(D16="",E16=""),"",IF(AND(ISNUMBER(D16),ISNUMBER(E16)),IF(E16>=D16,ROUND((E16-D16)*1440,0),"Check times"),"Check times")) | G16: =IF(ISNUMBER(F16),IF(Settings!$B$3<>"OK","Check settings",ROUNDUP(F16/Settings!$B$1,0)*Settings!$B$1),"") | H16: =IF(ISNUMBER(G16),G16/60,"") | I16: =IF(ISNUMBER(H16),ROUND(H16*Settings!$B$2,2),"") | J16: =IF(ISNUMBER(G16),G16-F16,"")
A17: 46307 | B17: Maple Dental | C17: Quarter planning | D17: 0.43055556 | E17: 0.48263889 | F17: =IF(AND(D17="",E17=""),"",IF(AND(ISNUMBER(D17),ISNUMBER(E17)),IF(E17>=D17,ROUND((E17-D17)*1440,0),"Check times"),"Check times")) | G17: =IF(ISNUMBER(F17),IF(Settings!$B$3<>"OK","Check settings",ROUNDUP(F17/Settings!$B$1,0)*Settings!$B$1),"") | H17: =IF(ISNUMBER(G17),G17/60,"") | I17: =IF(ISNUMBER(H17),ROUND(H17*Settings!$B$2,2),"") | J17: =IF(ISNUMBER(G17),G17-F17,"")
A18: 46307 | B18: Harbor Yoga | C18: Year-end checklist | D18: 0.59305556 | E18: 0.66597222 | F18: =IF(AND(D18="",E18=""),"",IF(AND(ISNUMBER(D18),ISNUMBER(E18)),IF(E18>=D18,ROUND((E18-D18)*1440,0),"Check times"),"Check times")) | G18: =IF(ISNUMBER(F18),IF(Settings!$B$3<>"OK","Check settings",ROUNDUP(F18/Settings!$B$1,0)*Settings!$B$1),"") | H18: =IF(ISNUMBER(G18),G18/60,"") | I18: =IF(ISNUMBER(H18),ROUND(H18*Settings!$B$2,2),"") | J18: =IF(ISNUMBER(G18),G18-F18,"")
A19: 46308 | B19: Pine Street Bakery | C19: Invoices | D19: 0.40625 | E19: 0.42083333 | F19: =IF(AND(D19="",E19=""),"",IF(AND(ISNUMBER(D19),ISNUMBER(E19)),IF(E19>=D19,ROUND((E19-D19)*1440,0),"Check times"),"Check times")) | G19: =IF(ISNUMBER(F19),IF(Settings!$B$3<>"OK","Check settings",ROUNDUP(F19/Settings!$B$1,0)*Settings!$B$1),"") | H19: =IF(ISNUMBER(G19),G19/60,"") | I19: =IF(ISNUMBER(H19),ROUND(H19*Settings!$B$2,2),"") | J19: =IF(ISNUMBER(G19),G19-F19,"")
F20: =IF(AND(D20="",E20=""),"",IF(AND(ISNUMBER(D20),ISNUMBER(E20)),IF(E20>=D20,ROUND((E20-D20)*1440,0),"Check times"),"Check times")) | G20: =IF(ISNUMBER(F20),IF(Settings!$B$3<>"OK","Check settings",ROUNDUP(F20/Settings!$B$1,0)*Settings!$B$1),"") | H20: =IF(ISNUMBER(G20),G20/60,"") | I20: =IF(ISNUMBER(H20),ROUND(H20*Settings!$B$2,2),"") | J20: =IF(ISNUMBER(G20),G20-F20,"")
F21: =IF(AND(D21="",E21=""),"",IF(AND(ISNUMBER(D21),ISNUMBER(E21)),IF(E21>=D21,ROUND((E21-D21)*1440,0),"Check times"),"Check times")) | G21: =IF(ISNUMBER(F21),IF(Settings!$B$3<>"OK","Check settings",ROUNDUP(F21/Settings!$B$1,0)*Settings!$B$1),"") | H21: =IF(ISNUMBER(G21),G21/60,"") | I21: =IF(ISNUMBER(H21),ROUND(H21*Settings!$B$2,2),"") | J21: =IF(ISNUMBER(G21),G21-F21,"")
F22: =IF(AND(D22="",E22=""),"",IF(AND(ISNUMBER(D22),ISNUMBER(E22)),IF(E22>=D22,ROUND((E22-D22)*1440,0),"Check times"),"Check times")) | G22: =IF(ISNUMBER(F22),IF(Settings!$B$3<>"OK","Check settings",ROUNDUP(F22/Settings!$B$1,0)*Settings!$B$1),"") | H22: =IF(ISNUMBER(G22),G22/60,"") | I22: =IF(ISNUMBER(H22),ROUND(H22*Settings!$B$2,2),"") | J22: =IF(ISNUMBER(G22),G22-F22,"")
F23: =IF(AND(D23="",E23=""),"",IF(AND(ISNUMBER(D23),ISNUMBER(E23)),IF(E23>=D23,ROUND((E23-D23)*1440,0),"Check times"),"Check times")) | G23: =IF(ISNUMBER(F23),IF(Settings!$B$3<>"OK","Check settings",ROUNDUP(F23/Settings!$B$1,0)*Settings!$B$1),"") | H23: =IF(ISNUMBER(G23),G23/60,"") | I23: =IF(ISNUMBER(H23),ROUND(H23*Settings!$B$2,2),"") | J23: =IF(ISNUMBER(G23),G23-F23,"")
F24: =IF(AND(D24="",E24=""),"",IF(AND(ISNUMBER(D24),ISNUMBER(E24)),IF(E24>=D24,ROUND((E24-D24)*1440,0),"Check times"),"Check times")) | G24: =IF(ISNUMBER(F24),IF(Settings!$B$3<>"OK","Check settings",ROUNDUP(F24/Settings!$B$1,0)*Settings!$B$1),"") | H24: =IF(ISNUMBER(G24),G24/60,"") | I24: =IF(ISNUMBER(H24),ROUND(H24*Settings!$B$2,2),"") | J24: =IF(ISNUMBER(G24),G24-F24,"")
F25: =IF(AND(D25="",E25=""),"",IF(AND(ISNUMBER(D25),ISNUMBER(E25)),IF(E25>=D25,ROUND((E25-D25)*1440,0),"Check times"),"Check times")) | G25: =IF(ISNUMBER(F25),IF(Settings!$B$3<>"OK","Check settings",ROUNDUP(F25/Settings!$B$1,0)*Settings!$B$1),"") | H25: =IF(ISNUMBER(G25),G25/60,"") | I25: =IF(ISNUMBER(H25),ROUND(H25*Settings!$B$2,2),"") | J25: =IF(ISNUMBER(G25),G25-F25,"")
F26: =IF(AND(D26="",E26=""),"",IF(AND(ISNUMBER(D26),ISNUMBER(E26)),IF(E26>=D26,ROUND((E26-D26)*1440,0),"Check times"),"Check times")) | G26: =IF(ISNUMBER(F26),IF(Settings!$B$3<>"OK","Check settings",ROUNDUP(F26/Settings!$B$1,0)*Settings!$B$1),"") | H26: =IF(ISNUMBER(G26),G26/60,"") | I26: =IF(ISNUMBER(H26),ROUND(H26*Settings!$B$2,2),"") | J26: =IF(ISNUMBER(G26),G26-F26,"")
F27: =IF(AND(D27="",E27=""),"",IF(AND(ISNUMBER(D27),ISNUMBER(E27)),IF(E27>=D27,ROUND((E27-D27)*1440,0),"Check times"),"Check times")) | G27: =IF(ISNUMBER(F27),IF(Settings!$B$3<>"OK","Check settings",ROUNDUP(F27/Settings!$B$1,0)*Settings!$B$1),"") | H27: =IF(ISNUMBER(G27),G27/60,"") | I27: =IF(ISNUMBER(H27),ROUND(H27*Settings!$B$2,2),"") | J27: =IF(ISNUMBER(G27),G27-F27,"")
F28: =IF(AND(D28="",E28=""),"",IF(AND(ISNUMBER(D28),ISNUMBER(E28)),IF(E28>=D28,ROUND((E28-D28)*1440,0),"Check times"),"Check times")) | G28: =IF(ISNUMBER(F28),IF(Settings!$B$3<>"OK","Check settings",ROUNDUP(F28/Settings!$B$1,0)*Settings!$B$1),"") | H28: =IF(ISNUMBER(G28),G28/60,"") | I28: =IF(ISNUMBER(H28),ROUND(H28*Settings!$B$2,2),"") | J28: =IF(ISNUMBER(G28),G28-F28,"")
F29: =IF(AND(D29="",E29=""),"",IF(AND(ISNUMBER(D29),ISNUMBER(E29)),IF(E29>=D29,ROUND((E29-D29)*1440,0),"Check times"),"Check times")) | G29: =IF(ISNUMBER(F29),IF(Settings!$B$3<>"OK","Check settings",ROUNDUP(F29/Settings!$B$1,0)*Settings!$B$1),"") | H29: =IF(ISNUMBER(G29),G29/60,"") | I29: =IF(ISNUMBER(H29),ROUND(H29*Settings!$B$2,2),"") | J29: =IF(ISNUMBER(G29),G29-F29,"")
F30: =IF(AND(D30="",E30=""),"",IF(AND(ISNUMBER(D30),ISNUMBER(E30)),IF(E30>=D30,ROUND((E30-D30)*1440,0),"Check times"),"Check times")) | G30: =IF(ISNUMBER(F30),IF(Settings!$B$3<>"OK","Check settings",ROUNDUP(F30/Settings!$B$1,0)*Settings!$B$1),"") | H30: =IF(ISNUMBER(G30),G30/60,"") | I30: =IF(ISNUMBER(H30),ROUND(H30*Settings!$B$2,2),"") | J30: =IF(ISNUMBER(G30),G30-F30,"")
F31: =IF(AND(D31="",E31=""),"",IF(AND(ISNUMBER(D31),ISNUMBER(E31)),IF(E31>=D31,ROUND((E31-D31)*1440,0),"Check times"),"Check times")) | G31: =IF(ISNUMBER(F31),IF(Settings!$B$3<>"OK","Check settings",ROUNDUP(F31/Settings!$B$1,0)*Settings!$B$1),"") | H31: =IF(ISNUMBER(G31),G31/60,"") | I31: =IF(ISNUMBER(H31),ROUND(H31*Settings!$B$2,2),"") | J31: =IF(ISNUMBER(G31),G31-F31,"")
... F64: =IF(AND(D64="",E64=""),"",IF(AND(ISNUMBER(D64),ISNUMBER(E64)),IF(E64>=D64,ROUND((E64-D64)*1440,0),"Check times"),"Check times")) | G64: =IF(ISNUMBER(F64),IF(Settings!$B$3<>"OK","Check settings",ROUNDUP(F64/Settings!$B$1,0)*Settings!$B$1),"") | H64: =IF(ISNUMBER(G64),G64/60,"") | I64: =IF(ISNUMBER(H64),ROUND(H64*Settings!$B$2,2),"") | J64: =IF(ISNUMBER(G64),G64-F64,"")

Sheet Settings
A1: Block size in minutes | B1: 15
A2: Hourly rate | B2: 85
A3: Settings check | B3: =IF(AND(ISNUMBER(B1),ISNUMBER(B2)),IF(AND(B1>=1,B1<=480,B1=INT(B1),B2>=0),"OK","Block: whole minutes from 1 to 480. Rate: 0 or more"),"Type a number in each yellow cell")
A5: Try 6 for six-minute blocks or 30 for half-hour blocks. A block of 1 bills every minute.

Sheet How to use
A1: Tidy Tabs: Round Billable Time Up to 15-Minute Blocks
A3: 1. Settings tab: type the block size in minutes in B1 (yellow, 15) and the hourly rate in B2 (yellow, $85.00). B3 shows OK when the block is a whole number from 1 to 480 and the rate is 0 or more.
A4: 2. Time log tab: one row per entry. Type the date, client, task, start and end time in A5:E64 (yellow). The sample is 15 fictional entries. Start and End are clock times on the same day.
A5: 3. Minutes worked, F5: =ROUND((E5-D5)*1440,0). A time is a fraction of a day, so times 1440 gives whole minutes. Rounding to a whole minute removes the tiny float tail (and any seconds).
A6: 4. Billed minutes, G5: =ROUNDUP(F5/Settings!$B$1,0)*Settings!$B$1. Divide by the block, round up to a whole number of blocks, multiply back. With a 15 minute block, 45 stays 45, 46 becomes 60, 0 stays 0, 1 becomes 15.
A7: 5. Billed hours, H5: =G5/60. Amount, I5: =ROUND(H5*Settings!$B$2,2). Extra minutes billed, J5: =G5-F5, the minutes added by rounding (never negative, always less than one block).
A8: 6. Summary, L5:M11: entries, total actual minutes, total billed minutes, the extra minutes billed because of rounding, the total amount, and the rows that show Check times. M11 shows OK when the settings are valid, every billed number is a whole number of blocks, the extra minutes are under one block and nothing is typed below row 64.
A9: 7. An End before the Start, or a Start without an End, shows Check times and is left out of the totals. A shift that runs past midnight is not handled here.
A10: 8. This is only the rounding arithmetic. It does not say what a client agreement allows.
A12: Clients, tasks and amounts are fictional. Checked in LibreOffice Calc only; not opened in Excel or Google Sheets.
A13: Google Sheets: File > Import > Upload this .xlsx.
